Workbook

Sheet Rekapitulasi Lapkeu
B2: PT. RUMA INOVASI INDONESIA
B3: Time Travel Design
B4: Laporan Keuangan
B5: 2026
B6: No | C6: Keterangan | D6: Debit | E6: Kredit | F6: Total
B7: Penghasilan / Omset / Nilai Kontrak (Revenue)
B8: 1 | C8: YP House - Yerry Primadi | D8: ='YP House - Yerry Primadi'!E11 -> 5800000 | F8: =SUM(D8:D25) -> 2275050682
B9: 2 | C9: SJ House - Tria Andika (LT1) | D9: ='SJ House - Tria Andika (LT1)'!E186 -> 273400000
B10: 3 | C10: TJ House - Tommy Saputra (LT1) | D10: ='TJ House - Tommy Saputra (LT1)'!E60 -> 75600000
B11: 4 | C11: TJ House - Tommy Saputra (LT2) | D11: ='TJ House - Tommy Saputra (LT2)'!E53 -> 66000000
B12: 5 | C12: RM Kost - Epi Suryadinata | D12: ='RM Kost - Epi Suryadinata'!E126 -> 450000000
B13: 6 | C13: CR House - Erick | D13: ='CR House - Erick'!E22 -> 15000000
B14: 7 | C14: SJ House - Tria Andika (LT2) | D14: ='SJ House - Tria Andika (LT2)'!E54 -> 51000000
B15: 8 | C15: DNN Office - Albert Anthonius Lim | D15: ='DNN Office - Kemayoran'!E205 -> 420238182
B16: 9 | C16: TJ House - Tommy Saputra (T3) | D16: ='TJ House - Tommy Saputra (T3)'!E67 -> 76000000
B17: 10 | C17: Kantor Blok SR - PT Indovisual | D17: ='Kantor Blok SR - Kemayoran'!E14 -> 6337500
B18: 11 | C18: Dapur Bebek - Enno Lerian | D18: ='Dapur Bebek - Bintaro'!E85 -> 97675000
B19: 12 | C19: PH House - Bogor | D19: ='PH House - Bogor'!E87 -> 388500000
B20: 13 | C20: SJ House - Tria Andika (LT 3) | D20: ='SJ House - Tria Andika (LT 3)'!E44 -> 47000000
B21: 14 | C21: SJ House - Tria Andika (KM) | D21: ='SJ House - Tria Andika (KM)'!E46 -> 58000000
B22: 15 | C22: FG House - Gregorius Figo | D22: ='FG House - Harapan Mulya'!E43 -> 35000000
B23: 16 | C23: 3HI - PT Indovisual | D23: ='3HI Office - Kemayoran'!E43 -> 109500000
B24: 17 | C24: Charity House - Pak Edwin | D24: ='Charity House - Bintaro'!E43 -> 100000000
B26: Harga Pokok Penjualan (HPP) / Cost Of Goods Sold (COGS)
B27: 1 | C27: Bahan Baku Utama / Material | E27: =SUM(D58:D74) -> 878710658 | F27: =SUM(E27:E30) -> 1595474478
B28: 2 | C28: Upah Tukang | E28: =SUM(D78:D94) -> 690743420
B29: 3 | C29: Sewa Alat Proyek | E29: =SUM(D98:D114) -> 3796000
B30: 4 | C30: Transportasi Lapangan | E30: =SUM(D118:D134) -> 22224400
B31: Laba Kotor (Gross Income) | D31: =F8-F27 -> 679576204
B32: Biaya Operasional (Operational Expenses)
B33: 1 | C33: Gaji dan Upah Karyawan | E33: ='Lapkeu Perusahaan'!J7 -> 119500000 | F33: =SUM(E33:E39) -> 2.3365545e+08
B34: 2 | C34: Transportasi Operasional | E34: ='Lapkeu Perusahaan'!J8 -> 23596236
B35: 3 | C35: Biaya Konsumsi Kantor | E35: ='Lapkeu Perusahaan'!J9 -> 30134858
B36: 4 | C36: Biaya Jamuan / Representasi | E36: ='Lapkeu Perusahaan'!J10 -> 4129979
B37: 5 | C37: Biaya Marketing | E37: ='Lapkeu Perusahaan'!J11 -> 34329899
B38: 6 | C38: Kebutuhan Workshop | E38: ='Lapkeu Perusahaan'!J17 -> 21895000
B39: 7 | C39: Biaya Administrasi Finansial | E39: ='Lapkeu Perusahaan'!J12 -> 69477.29
B40: Laba Bersih (Net Income) | D40: =D31-F33 -> 4.4592075e+08
B41: Biaya Aset dan Investasi (Capital Expenditure)
B42: 1 | C42: Renovasi Kantor | E42: ='Lapkeu Perusahaan'!J13 -> 33827440 | F42: =SUM(E42:E45) -> 51714617
B43: 2 | C43: Legalitas Perusahaan | E43: ='Lapkeu Perusahaan'!J14 -> 7810000
B44: 3 | C44: Inventaris | E44: ='Lapkeu Perusahaan'!J15 -> 7678176
B45: 4 | C45: Perangkat Gadget | E45: ='Lapkeu Perusahaan'!J16 -> 2399001
B46: Total Kas | D46: =F8+D39 -> 2275050682 | E46: =F27+F33+F42 -> 1.8808445e+09 | F46: =D46-E46 -> 3.9420614e+08
E47: Kas Awal 2025 | F47: ='Lapkeu Perusahaan'!E7 -> 12500180
E48: Kas Saat Ini | F48: =F46+F47 -> 4.0670632e+08
E50: Kasbon Om Doddy | F50: ='Lapkeu Perusahaan'!G475 -> 73500000
E51: Kasbon Emir | F51: ='Lapkeu Perusahaan'!G476 -> 113111100
E52: Kasbon Dustin | F52: ='Lapkeu Perusahaan'!G477 -> 188383595
F54: =F48-SUM(F50:F52) -> 31711623
F55: =F54-'Lapkeu Perusahaan'!G479 -> 33659290
B57: Belanja Bahan Baku
B58: 1 | C58: YP House - Yerry Primadi | D58: ='YP House - Yerry Primadi'!J7 -> 163000
B59: 2 | C59: SJ House - Tria Andika (LT1) | D59: ='SJ House - Tria Andika (LT1)'!J7 -> 104219718
B60: 3 | C60: TJ House - Tommy Saputra (LT1) | D60: ='TJ House - Tommy Saputra (LT1)'!J7 -> 38502983
B61: 4 | C61: TJ House - Tommy Saputra (LT2) | D61: ='TJ House - Tommy Saputra (LT2)'!J7 -> 25117904
B62: 5 | C62: RM Kost - Epi Suryadinata | D62: ='RM Kost - Epi Suryadinata'!J7 -> 171426833
B63: 6 | C63: CR House - Erick | D63: ='CR House - Erick'!J7 -> 3937635
B64: 7 | C64: SJ House - Tria Andika (LT2) | D64: ='SJ House - Tria Andika (LT2)'!J7 -> 17453043
B65: 8 | C65: DNN Office - Albert Anthonius Lim | D65: ='DNN Office - Kemayoran'!J7 -> 195624426
B66: 9 | C66: TJ House - Tommy Saputra (T3) | D66: ='TJ House - Tommy Saputra (T3)'!J7 -> 31804249
B67: 10 | C67: Kantor Blok SR - PT Indovisual | D67: ='Kantor Blok SR - Kemayoran'!J7 -> 2232245
B68: 11 | C68: Dapur Bebek - Enno Lerian | D68: ='Dapur Bebek - Bintaro'!J7 -> 54589797
B69: 12 | C69: PH House - Bogor | D69: ='PH House - Bogor'!J7 -> 123084475
B70: 13 | C70: SJ House - Tria Andika (LT 3) | D70: ='SJ House - Tria Andika (LT 3)'!J7 -> 22743524
B71: 14 | C71: SJ House - Tria Andika (KM) | D71: ='SJ House - Tria Andika (KM)'!J7 -> 34348151
B72: 15 | C72: FG House - Gregorius Figo | D72: ='FG House - Harapan Mulya'!J7 -> 6872375
B73: 16 | C73: 3HI - PT Indovisual | D73: ='3HI Office - Kemayoran'!J7 -> 17230300
B74: 17 | C74: Charity House - Pak Edwin | D74: ='Charity House - Bintaro'!J7 -> 29360000
B77: Upah Tukang
B78: 1 | C78: YP House - Yerry Primadi | D78: ='YP House - Yerry Primadi'!J8 -> 0
B79: 2 | C79: SJ House - Tria Andika (LT1) | D79: ='SJ House - Tria Andika (LT1)'!J8 -> 78367000
B80: 3 | C80: TJ House - Tommy Saputra (LT1) | D80: ='TJ House - Tommy Saputra (LT1)'!J8 -> 18200000
B81: 4 | C81: TJ House - Tommy Saputra (LT2) | D81: ='TJ House - Tommy Saputra (LT2)'!J8 -> 17800000
B82: 5 | C82: RM Kost - Epi Suryadinata | D82: ='RM Kost - Epi Suryadinata'!J8 -> 148753670
B83: 6 | C83: CR House - Erick | D83: ='CR House - Erick'!J8 -> 4000000
B84: 7 | C84: SJ House - Tria Andika (LT2) | D84: ='SJ House - Tria Andika (LT2)'!J8 -> 13833000
B85: 8 | C85: DNN Office - Albert Anthonius Lim | D85: ='DNN Office - Kemayoran'!J8 -> 157008500
B86: 9 | C86: TJ House - Tommy Saputra (T3) | D86: ='TJ House - Tommy Saputra (T3)'!J8 -> 20550000
B87: 10 | C87: Kantor Blok SR - PT Indovisual | D87: ='Kantor Blok SR - Kemayoran'!J8 -> 1345000
B88: 11 | C88: Dapur Bebek - Enno Lerian | D88: ='Dapur Bebek - Bintaro'!J8 -> 50119400
B89: 12 | C89: PH House - Bogor | D89: ='PH House - Bogor'!J8 -> 131808350
B90: 13 | C90: SJ House - Tria Andika (LT 3) | D90: ='SJ House - Tria Andika (LT 3)'!J8 -> 18725000
B91: 14 | C91: SJ House - Tria Andika (KM) | D91: ='SJ House - Tria Andika (KM)'!J8 -> 13524000
B92: 15 | C92: FG House - Gregorius Figo | D92: ='FG House - Harapan Mulya'!J8 -> 4927000
B93: 16 | C93: 3HI - PT Indovisual | D93: ='3HI Office - Kemayoran'!J8 -> 10782500
B94: 17 | C94: Charity House - Pak Edwin | D94: ='Charity House - Bintaro'!J8 -> 1000000
B97: Sewa Alat Proyek
B98: 1 | C98: YP House - Yerry Primadi | D98: ='YP House - Yerry Primadi'!J9 -> 0
B99: 2 | C99: SJ House - Tria Andika (LT1) | D99: ='SJ House - Tria Andika (LT1)'!J9 -> 0
B100: 3 | C100: TJ House - Tommy Saputra (LT1) | D100: ='TJ House - Tommy Saputra (LT1)'!J9 -> 0
B101: 4 | C101: TJ House - Tommy Saputra (LT2) | D101: ='TJ House - Tommy Saputra (LT2)'!J9 -> 0
B102: 5 | C102: RM Kost - Epi Suryadinata | D102: ='RM Kost - Epi Suryadinata'!J9 -> 0
B103: 6 | C103: CR House - Erick | D103: ='CR House - Erick'!J9 -> 0
B104: 7 | C104: SJ House - Tria Andika (LT2) | D104: ='SJ House - Tria Andika (LT2)'!J9 -> 0
B105: 8 | C105: DNN Office - Albert Anthonius Lim | D105: ='DNN Office - Kemayoran'!J9 -> 0
B106: 9 | C106: TJ House - Tommy Saputra (T3) | D106: ='TJ House - Tommy Saputra (T3)'!J9 -> 0
B107: 10 | C107: Kantor Blok SR - PT Indovisual | D107: ='Kantor Blok SR - Kemayoran'!J9 -> 0
B108: 11 | C108: Dapur Bebek - Enno Lerian | D108: ='Dapur Bebek - Bintaro'!J9 -> 0
B109: 12 | C109: PH House - Bogor | D109: ='PH House - Bogor'!J9 -> 3796000
...

Sheet Lapkeu Perusahaan
B2: PT. RUMA INOVASI INDONESIA
B3: Time Travel Design
B4: Laporan Keuangan
B5: 2026
B6: No | C6: Tanggal | D6: Keterangan | E6: Debit | F6: Kredit | G6: Saldo Akhir | I6: Pengelompokan | J6: Total
B7: 1 | C7: 46023 | D7: Kas Modal 2025 | E7: 12500180 | G7: =E7 -> 12500180 | I7: Gaji dan Upah Karyawan | J7: =F15+F16+F27+F28+F43+F44+F76+F77+F118+F119+F124+F188+F189+F200+SUM(F294:F295)+F305+F368+F380+F381+F429+F430+F440 -> 119500000
B8: 2 | C8: 46033 | D8: WPC Kebutuhan Kantor | F8: 359990 | G8: =G7-F8 -> 12140190 | I8: Transportasi Operasional | J8: =SUM(K8:L8) -> 23596236 | K8: =SUM(F21,F23,F34,F39,F45:F46,F48:F49,F58,F64:F65,F67,F72,F74,F78,F94,F97:F98,F104:F105,F107,F109,F113:F115,F123,F125,F132,F135,F140,F150,F154:F155,F159:F160,F162,F166,F169:F170,F173,F181:F182,F184,F186:F187,F190,F192:F193,F198,F202,F208,F217,F220,F236,F242,F256) -> 12575255 | L8: =SUM(F257:F258,F270,F287,F289,F293,F312,F316,F326:F327,F337,F346:F348,F352,F354,F356,F360:F361,F363:F364,F374,F377,F379,F382:F383,F394,F400,F402,F404,F408:F409,F418:F419,F421,F428,F433,F446:F447,F455) -> 11020981
B9: 3 | C9: 46038 | D9: Biaya Administrasi BCA | F9: 10000 | G9: =G8-F9 -> 12130190 | I9: Biaya Konsumsi Kantor | J9: =SUM(K9:L9) -> 30134858 | K9: =SUM(F30:F33,F37,F51,F54:F57,F59:F61,F66,F69:F71,F73,F75,F79,F84,F86:F87,F92,F95:F96,F99:F103,F110,F116:F117,F120:F121,F129:F131,F133,F136,F139,F141:F143,F145,F148:F149,F151,F153,F156:F158,F171,F175:F176,F185,F191,F195,F201,F204:F206,F209,F211:F215,F218,F222:F226,F229:F230,F232,F235,F239,F243,F247,F250:F251,F254) -> 14647097 | L9: =SUM(F263,F265:F268,F271:F272,F275:F277,F279:F283,F286,F290,F297:F299,F302,F306:F307,F309,F314:F315,F319:F325,F328:F331,F333:F336,F338,F340:F345,F349:F351,F353,F355,F357,F359,F362,F365,F369:F373,F375:F376,F384,F387:F390,F392,F395:F399,F401,F403,F407,F410:F412,F415:F417,F420,F422:F423,F425,F427,F432,F436:F439,F443:F444,F448,F451,F454,F456:F461) -> 15487761
B10: 4 | C10: 46039 | D10: Final Project - YP House | E10: ='YP House - Yerry Primadi'!G11 -> 5637000 | G10: =G9+E10 -> 17767190 | I10: Biaya Jamuan / Representasi | J10: =F36+F144+F233+F303+F313+F414+F431+SUM(F449:F450) -> 4129979
B11: 5 | C11: 46039 | D11: Triplek Kebutuhan Kantor | F11: 234000 | G11: =G10-F11 -> 17533190 | I11: Biaya Marketing | J11: =F17+F20+F22+F24+F35+F41+F63+F80+F174+F245+F252+F284+F339+F413+F435 -> 34329899
B12: 6 | C12: 46041 | D12: Stop Kontak Kebutuhan Kantor | F12: 280900 | G12: =G11-F12 -> 17252290 | I12: Biaya Administrasi Finansial | J12: =F9-E18+F19+F25-E29+F42-E52+F53+F68-E89+F90+F108-E126+F127+F128-E196+F197+F203-E310+F311+F318-E385+F386+F391-E441+F442+F453 -> 69477.29
B13: 7 | C13: 46041 | D13: HPL Kebutuhan Kantor | F13: 270000 | G13: =G12-F13 -> 16982290 | I13: Renovasi Kantor | J13: =F8+SUM(F11:F14)+F81+F85+F91+F93+F146+F163+F167+SUM(F177:F178)+F180+F216+F219+F221+SUM(F227:F228)+F231+F234+SUM(F237:F238)+F246+F249+F253+F255+F260+F273+F288+F291+SUM(F366:F367)+SUM(F405:F406) -> 33827440
B14: 8 | C14: 46042 | D14: Lembur Meja Kantor Mas Imam | F14: 150000 | G14: =G13-F14 -> 16832290 | I14: Legalitas Perusahaan | J14: =F38+F47+F134+F137+F285+F332+F378 -> 7810000
B15: 9 | C15: 46047 | D15: Gajian Emir - Januari | F15: 5000000 | G15: =G14-F15 -> 11832290 | I15: Inventaris | J15: =F50+F62+F82+F106+F147+F152+F161+F164+F168+F199+F434+F445 -> 7678176
B16: 10 | C16: 46047 | D16: Gajian Dustin - Januari | F16: 5000000 | G16: =G15-F16 -> 6832289.9 | I16: Perangkat Gadget | J16: =F122 -> 2399001
B17: 11 | C17: 46050 | D17: Print Flyer | F17: 357000 | G17: =G16-F17 -> 6475289.9 | I17: Kebutuhan Workshop | J17: =F172+F179+F183+F194+F207+F241+F248+F259+SUM(F261:F262)+F264+F274+F278+F296+SUM(F300:F301)+F304+F308+F317+F358+F292 -> 21895000
B18: 12 | C18: 46053 | D18: Bunga Bank BCA | E18: 251.4 | G18: =G17+E18 -> 6475541.3 | J18: =SUM(J7:J17)+E18+E29+E52+E89+E126+E196+E310+E385+E441 -> 2.854082e+08
B19: 13 | C19: 46053 | D19: Pajak Bunga Bank BCA | F19: 50.28 | G19: =G18-F19 -> 6475491 | J19: =F473-J18 -> 550600
B20: 14 | C20: 46055 | D20: Instagram Ads | F20: 251000 | G20: =G19-F20 -> 6224491
B21: 15 | C21: 46057 | D21: Reimburse Bensin Emir sebar Brosur | F21: 126400 | G21: =G20-F21 -> 6098091
B22: 16 | C22: 46062 | D22: Print Company Profile | F22: 257000 | G22: =G21-F22 -> 5841091
B23: 17 | C23: 46069 | D23: Reimburse Bensin Emir ke Bandung | F23: 609000 | G23: =G22-F23 -> 5232091
B24: 18 | C24: 46072 | D24: Print Brosur Murah | F24: 120000 | G24: =G23-F24 -> 5112091
B25: 19 | C25: 46073 | D25: Biaya Administrasi BCA | F25: 10000 | G25: =G24-F25 -> 5102091
B26: 20 | C26: 46076 | D26: Final Project - SJ House (LT1) | E26: ='SJ House - Tria Andika (LT1)'!G186 -> 84022482 | G26: =G25+E26 -> 89124573
B27: 21 | C27: 46079 | D27: Gajian Emir - Februari | F27: 5000000 | G27: =G26-F27 -> 84124573
B28: 22 | C28: 46079 | D28: Gajian Dustin - Februari | F28: 5000000 | G28: =G27-F28 -> 79124573
B29: 23 | C29: 46081 | D29: Bunga Bank BCA | E29: 79.67 | G29: =G28+E29 -> 79124653
B30: 24 | C30: 46084 | D30: Bukber Kantor | F30: =292000+24000 -> 316000 | G30: =G29-F30 -> 78808653
B31: 25 | C31: 46085 | D31: Bukber Kantor | F31: =136000+10000 -> 146000 | G31: =G30-F31 -> 78662653
B32: 26 | C32: 46086 | D32: Bukber Kantor | F32: 70000 | G32: =G31-F32 -> 78592653
B33: 27 | C33: 46088 | D33: Makan Minum Mang Edi | F33: =32000+23700 -> 55700 | G33: =G32-F33 -> 78536953
B34: 28 | C34: 46093 | D34: Kampas Rem Road Glide | F34: 230000 | G34: =G33-F34 -> 78306953
B35: 29 | C35: 46094 | D35: Print Fyler | F35: 890000 | G35: =G34-F35 -> 77416953
B36: 30 | C36: 46097 | D36: Hampers Lebaran Bu Devi dan Mas Arya | F36: 438000 | G36: =G35-F36 -> 76978953
B37: 31 | C37: 46097 | D37: Bukber Kantor | F37: 417200 | G37: =G36-F37 -> 76561753
B38: 32 | C38: 46097 | D38: DP Balik Nama Akta Perusahaan | F38: 3002500 | G38: =G37-F38 -> 73559253
B39: 33 | C39: 46098 | D39: Ganti Ban Depan Road Glide | F39: 280000 | G39: =G38-F39 -> 73279253
B40: 34 | C40: 46098 | D40: Final Project - TJ House (LT1) | E40: ='TJ House - Tommy Saputra (LT1)'!G60 -> 16959517 | G40: =G39+E40 -> 90238770
B41: 35 | C41: 46101 | D41: Fee Marketing Darren | F41: 1500000 | G41: =G40-F41 -> 88738770
B42: 36 | C42: 46101 | D42: Biaya Administrasi BCA | F42: 10000 | G42: =G41-F42 -> 88728770
B43: 37 | C43: 46107 | D43: Gajian Emir - Maret | F43: 5000000 | G43: =G42-F43 -> 83728770
B44: 38 | C44: 46107 | D44: Gajian Dustin - Maret | F44: 5000000 | G44: =G43-F44 -> 78728770
B45: 39 | C45: 46107 | D45: Reimburse Bensin Dustin sebar Brosur | F45: 100000 | G45: =G44-F45 -> 78628770
B46: 40 | C46: 46109 | D46: Reimburse Bensin Dustin Ngukur | F46: 50000 | G46: =G45-F46 -> 78578770
B47: 41 | C47: 46110 | D47: Termin II Balik Nama Akta Perusahaan | F47: 1002500 | G47: =G46-F47 -> 77576270
B48: 42 | C48: 46111 | D48: Reimburse Bensin Emir Meeting | F48: 132000 | G48: =G47-F48 -> 77444270
B49: 43 | C49: 46111 | D49: Reimburse Bensin Dustin Meeting | F49: 110000 | G49: =G48-F49 -> 77334270
B50: 44 | C50: 46111 | D50: Beli Mesin Jigsaw | F50: 310000 | G50: =G49-F50 -> 77024270
B51: 45 | C51: 46112 | D51: Makan Minum Tukang | F51: 57000 | G51: =G50-F51 -> 76967270
B52: 46 | C52: 46112 | D52: Bunga Bank BCA | E52: 1691.5 | G52: =G51+E52 -> 76968961
B53: 47 | C53: 46112 | D53: Pajak Bunga Bank BCA | F53: 338.3 | G53: =G52-F53 -> 76968623
B54: 48 | C54: 46116 | D54: Makan Minum Tukang | F54: 85000 | G54: =G53-F54 -> 76883623
B55: 49 | C55: 46117 | D55: Makan Minum Tukang | F55: 266000 | G55: =G54-F55 -> 76617623
B56: 50 | C56: 46118 | D56: Makan Minum Tukang | F56: 13000 | G56: =G55-F56 -> 76604623
B57: 51 | C57: 46120 | D57: Makan Soto di Bogor | F57: 255000 | G57: =G56-F57 -> 76349623
B58: 52 | C58: 46123 | D58: Reimburse Transport Emir | F58: 503000 | G58: =G57-F58 -> 75846623
B59: 53 | C59: 46127 | D59: Rokok dan Minum | F59: 49000 | G59: =G58-F59 -> 75797623
B60: 54 | C60: 46127 | D60: Makan Siang | F60: 266750 | G60: =G59-F60 -> 75530873
B61: 55 | C61: 46128 | D61: Rokok dan Minum | F61: 90000 | G61: =G60-F61 -> 75440873
B62: 56 | C62: 46130 | D62: Beli Mesin Circle | F62: 1362400 | G62: =G61-F62 -> 74078473
B63: 57 | C63: 46130 | D63: Fee Marketing Mas Rizky | F63: 500000 | G63: =G62-F63 -> 73578473
B64: 58 | C64: 46131 | D64: Reimburse Transport Emir | F64: 298000 | G64: =G63-F64 -> 73280473
... B82: 76 | C82: 46140 | D82: Beli Mesin Gerinda | F82: 587000 | G82: =G81-F82 -> 52132573
B83: 77 | C83: 46141 | D83: Final Project - TJ House (LT2) | E83: ='TJ House - Tommy Saputra (LT2)'!G53 -> 22757096 | G83: =G82+E83 -> 74889669
B84: 78 | C84: 46141 | D84: Beli Rokok | F84: 38000 | G84: =G83-F84 -> 74851669
B85: 79 | C85: 46142 | D85: Belanjaan Renov Kantor | F85: 758000 | G85: =G84-F85 -> 74093669
B86: 80 | C86: 46142 | D86: Makan Bebek Rojo Sambal | F86: 74000 | G86: =G85-F86 -> 74019669
B87: 81 | C87: 46142 | D87: Makan Soto | F87: 77000 | G87: =G86-F87 -> 73942669
B88: 82 | C88: 46142 | D88: Final Project - RM Kost | E88: ='RM Kost - Epi Suryadinata'!G126 -> 122996697 | G88: =G87+E88 -> 1.9693937e+08
B89: 83 | C89: 46142 | D89: Bunga Bank BCA | E89: 781.75 | G89: =G88+E89 -> 1.9694015e+08
B90: 84 | C90: 46142 | D90: Pajak Bunga Bank BCA | F90: 156.35 | G90: =G89-F90 -> 1.9693999e+08
B91: 85 | C91: 46143 | D91: Belanjaan Renov Kantor | F91: 140000 | G91: =G90-F91 -> 1.9679999e+08
B92: 86 | C92: 46143 | D92: Makan Rokok Tukang | F92: 31500 | G92: =G91-F92 -> 1.9676849e+08
B93: 87 | C93: 46143 | D93: Gajian Mang Edi Renov Kantor | F93: 4000000 | G93: =G92-F93 -> 1.9276849e+08
B94: 88 | C94: 46143 | D94: Reimburse Bensin Emir | F94: 423500 | G94: =G93-F94 -> 1.9234499e+08
B95: 89 | C95: 46143 | D95: Makan Nakotiam Bogor | F95: 156200 | G95: =G94-F95 -> 1.9218879e+08
B96: 90 | C96: 46143 | D96: Makan Sate Maranggi Bogor | F96: 291500 | G96: =G95-F96 -> 1.9189729e+08
B97: 91 | C97: 46145 | D97: Reimburse Bensin Emir | F97: 398000 | G97: =G96-F97 -> 1.9149929e+08
B98: 92 | C98: 46146 | D98: Grab Mas Imam | F98: 171000 | G98: =G97-F98 -> 1.9132829e+08
B99: 93 | C99: 46149 | D99: Makan Sate | F99: 31000 | G99: =G98-F99 -> 1.9129729e+08
B100: 94 | C100: 46150 | D100: Makan Bubur | F100: 50000 | G100: =G99-F100 -> 1.9124729e+08
B101: 95 | C101: 46150 | D101: Kopi Kenangan | F101: 42000 | G101: =G100-F101 -> 1.9120529e+08
... B110: 104 | C110: 46160 | D110: Makan Siang | F110: 257400 | G110: =G109-F110 -> 1.8847075e+08
B111: 105 | C111: 46160 | D111: Final Project - CR House | E111: ='CR House - Erick'!G22 -> 6588365 | G111: =G110+E111 -> 1.9505912e+08
B112: 106 | C112: 46160 | D112: Final Project - SJ House (LT2) | E112: ='SJ House - Tria Andika (LT2)'!G54 -> 19146957 | G112: =G111+E112 -> 2.1420607e+08
B113: 107 | C113: 46161 | D113: Reimburse Transport Dustin | F113: 100000 | G113: =G112-F113 -> 2.1410607e+08
B114: 108 | C114: 46162 | D114: Grab Mas Imam Ke Bayem | F114: 185000 | G114: =G113-F114 -> 2.1392107e+08
B115: 109 | C115: 46165 | D115: Reimburse Transport Dustin | F115: 100000 | G115: =G114-F115 -> 2.1382107e+08
B116: 110 | C116: 46165 | D116: Makan Siang | F116: 334400 | G116: =G115-F116 -> 2.1348667e+08
B117: 111 | C117: 46169 | D117: Makan Minum Tukang | F117: 48000 | G117: =G116-F117 -> 2.1343867e+08
B118: 112 | C118: 46170 | D118: Gajian Dustin - Mei | F118: 5000000 | G118: =G117-F118 -> 2.0843867e+08
B119: 113 | C119: 46170 | D119: Gajian Emir - Mei | F119: 5000000 | G119: =G118-F119 -> 2.0343867e+08
B120: 114 | C120: 46171 | D120: Makan Sukiyaki Rin | F120: 1662595 | G120: =G119-F120 -> 2.0177608e+08
B121: 115 | C121: 46171 | D121: Sayap Suci | F121: 167600 | G121: =G120-F121 -> 2.0160848e+08
B122: 116 | C122: 46171 | D122: Beli HP Mas Imam | F122: 2399001 | G122: =G121-F122 -> 1.9920948e+08
B123: 117 | C123: 46172 | D123: Reimburse Transport Dustin | F123: 150000 | G123: =G122-F123 -> 1.9905948e+08
B124: 118 | C124: 46172 | D124: Gajian Bumi - Mei | F124: 1500000 | G124: =G123-F124 -> 1.9755948e+08
B125: 119 | C125: 46173 | D125: Reimburse Transport Emir | F125: 576385 | G125: =G124-F125 -> 1.9698309e+08
B126: 120 | C126: 46173 | D126: Bunga Bank BCA | E126: 6816.72 | G126: =G125+E126 -> 196989909
...

Sheet Charity House - Bintaro
B2: Time Travel Design
B3: Charity House - Bintaro
B4: Laporan Keuangan
B5: 2026
B6: No | C6: Tanggal | D6: Keterangan | E6: Debit | F6: Kredit | G6: Saldo Akhir | I6: Pengelompokan | J6: Total
B7: 1 | C7: 46288 | D7: Pembayaran Tahap I | E7: 100000000 | I7: Bahan Baku Utama / Material | J7: =SUM(F8,F10:F12) -> 29360000
B8: 2 | C8: 46300 | D8: Material | F8: 3513000 | I8: Upah Tukang | J8: =F9 -> 1000000
B9: 3 | C9: 46300 | D9: Kasbon Mang Rian | F9: 1000000 | I9: Sewa Alat Proyek
B10: 4 | C10: 46301 | D10: Batu Kali | F10: 2500000 | I10: Transportasi Lapangan
B11: 5 | C11: 46301 | D11: Baja dan Pembesian | F11: 21382000 | J11: =SUM(J7:J10) -> 30360000
B12: 6 | C12: 46301 | D12: Baja | F12: 1965000
B13: 7 | C13: 46304 | D13: Material | F13: 1125000
B14: 8 | C14: 46304 | D14: Gajian Mang Rian | F14: 6523000
B15: 9
B16: 10
B17: 11
B18: 12
B19: 13
B20: 14
B21: 15
B22: 16
B23: 17
B24: 18
B25: 19
B26: 20
... B38: 32
B43: Jumlah | E43: =SUM(E7:E42) -> 100000000 | F43: =SUM(F7:F42) -> 38008000 | G43: =E43-F43 -> 61992000
G44: =G43/E43 -> 0.61992

Sheet 3HI Office - Kemayoran
B2: Time Travel Design
B3: 3HI Office - Kemayoran
B4: Laporan Keuangan
B5: 2026
B6: No | C6: Tanggal | D6: Keterangan | E6: Debit | F6: Kredit | G6: Saldo Akhir | I6: Pengelompokan | J6: Total
B7: 1 | C7: 46288 | D7: Pembayaran Tahap I | E7: 109500000 | G7: =E7 -> 109500000 | I7: Bahan Baku Utama / Material | J7: =SUM(F9:F11)+F13+F16+F18 -> 17230300
B8: 2 | C8: 46290 | D8: Kasbon Mas Rosidin | F8: 1502500 | G8: =G7-F8 -> 107997500 | I8: Upah Tukang | J8: =F8+F12+F14+F17 -> 10782500
B9: 3 | C9: 46291 | D9: Material Metal Stud | F9: 3895000 | G9: =G8-F9 -> 104102500 | I9: Sewa Alat Proyek
B10: 4 | C10: 46291 | D10: Material Steger dan Paku | F10: 523000 | G10: =G9-F10 -> 103579500 | I10: Transportasi Lapangan | J10: =F15 -> 500000
B11: 5 | C11: 46292 | D11: Bongkaran Alumunium | F11: 2452500 | G11: =G10-F11 -> 101127000 | J11: =SUM(J7:J10) -> 28512800
B12: 6 | C12: 46293 | D12: Kasbon Mas Rosidin | F12: 2502500 | G12: =G11-F12 -> 98624500
B13: 7 | C13: 46294 | D13: Material Gypsum | F13: 5091000 | G13: =G12-F13 -> 93533500 | I13: Total Kasbon Mas Alan | J13: =F17 -> 2000000
B14: 8 | C14: 46297 | D14: Gajian Mas Rosidin | F14: 4777500 | G14: =G13-F14 -> 88756000 | I14: Sisa Kasbon Mas Alan | J14: =10000000-J13 -> 8000000
B15: 9 | C15: 46297 | D15: Transport Tukang | F15: 500000 | G15: =G14-F15 -> 88256000
B16: 10 | C16: 46300 | D16: Material Alumunium | F16: 4332800 | G16: =G15-F16 -> 83923200
B17: 11 | C17: 46300 | D17: Kasbon Mas Alan | F17: 2000000 | G17: =G16-F17 -> 81923200
B18: 12 | C18: 46303 | D18: Material Kabel dan Tang | F18: 936000 | G18: =G17-F18 -> 80987200
B19: 13 | C19: 46303 | D19: Material Alumunium | F19: 790500
B20: 14 | C20: 46304 | D20: Material Gypsum | F20: 1169000
B21: 15 | C21: 46304 | D21: Gajian Mas Rosidin | F21: 6174690
B22: 16 | C22: 46304 | D22: Material | F22: 2640000
B23: 17
B24: 18
B25: 19
B26: 20
B27: 21
B28: 22
B29: 23
B30: 24
B31: 25
B32: 26
B33: 27
B34: 28
... B38: 32
B43: Jumlah | E43: =SUM(E7:E42) -> 109500000 | F43: =SUM(F7:F42) -> 39286990 | G43: =E43-F43 -> 70213010
G44: =G43/E43 -> 0.6412147

Sheet FG House - Harapan Mulya
B2: Time Travel Design
B3: FG House - Harapan Mulya
B4: Laporan Keuangan
B5: 2026
B6: No | C6: Tanggal | D6: Keterangan | E6: Debit | F6: Kredit | G6: Saldo Akhir | I6: Pengelompokan | J6: Total
B7: 1 | C7: 46288 | D7: Pembayaran Tahap I | E7: 35000000 | G7: =E7 -> 35000000 | I7: Bahan Baku Utama / Material | J7: =F8+SUM(F10:F11,F13:F14)+SUM(F16:F18,F20:F21) -> 6872375
B8: 2 | C8: 46293 | D8: Material | F8: 2527000 | G8: =G7-F8 -> 32473000 | I8: Upah Tukang | J8: =F9+F15+F22 -> 4927000
B9: 3 | C9: 46294 | D9: Kasbon Mang Edi | F9: 1000000 | G9: =G8-F9 -> 31473000 | I9: Sewa Alat Proyek
B10: 4 | C10: 46295 | D10: Material | F10: 328000 | G10: =G9-F10 -> 31145000 | I10: Transportasi Lapangan | J10: =F12+F19 -> 200000
B11: 5 | C11: 46295 | D11: Materiap Atap uPVC | F11: 600000 | G11: =G10-F11 -> 30545000 | J11: =SUM(J7:J10) -> 11999375
B12: 6 | C12: 46296 | D12: Lalamove Atap | F12: 100000 | G12: =G11-F12 -> 30445000
B13: 7 | C13: 46296 | D13: Aquaproof | F13: 245000 | G13: =G12-F13 -> 30200000
B14: 8 | C14: 46297 | D14: Isi Token | F14: 53000 | G14: =G13-F14 -> 30147000
B15: 9 | C15: 46297 | D15: Gajian Mang Edi | F15: 2927000 | G15: =G14-F15 -> 27220000
B16: 10 | C16: 46298 | D16: Material | F16: 832000 | G16: =G15-F16 -> 26388000
B17: 11 | C17: 46301 | D17: Material | F17: 848000 | G17: =G16-F17 -> 25540000
B18: 12 | C18: 46301 | D18: Shadowline | F18: 96000 | G18: =G17-F18 -> 25444000
B19: 13 | C19: 46301 | D19: Uang Satpam | F19: 100000 | G19: =G18-F19 -> 25344000
B20: 14 | C20: 46301 | D20: Keramik | F20: 1218375 | G20: =G19-F20 -> 24125625
B21: 15 | C21: 46301 | D21: Lalamove Keramik | F21: 125000 | G21: =G20-F21 -> 24000625
B22: 16 | C22: 46301 | D22: Kasbon Mang Edi | F22: 1000000 | G22: =G21-F22 -> 23000625
B23: 17 | C23: 46305 | D23: Gajian Mang Edi | F23: 2315000
B24: 18
B25: 19
B26: 20
B27: 21
B28: 22
B29: 23
B30: 24
B31: 25
B32: 26
B33: 27
B34: 28
B35: 29
... B38: 32
B43: Jumlah | E43: =SUM(E7:E42) -> 35000000 | F43: =SUM(F7:F42) -> 14314375 | G43: =E43-F43 -> 20685625
G44: =G43/E43 -> 0.59101786

Sheet PH House - Bogor
B2: Time Travel Design
B3: Pakuan Hill House - Bogor
B4: Laporan Keuangan
B5: 2026
B6: No | C6: Tanggal | D6: Keterangan | E6: Debit | F6: Kredit | G6: Saldo Akhir | I6: Pengelompokan | J6: Total
B7: 1 | C7: 46217 | D7: Print RAB | F7: 48000 | G7: =-F7 -> -48000 | I7: Bahan Baku Utama / Material | J7: =F7+SUM(F11:F14)+F18+SUM(F20:F25)+F27+SUM(F29:F30)+F34+SUM(F36:F37)+SUM(F40:F42)+F44+SUM(F46:F48)+SUM(F50:F52)+SUM(F58:F61,F64:F65)+SUM(F68:F70)+F72+SUM(F75:F76)+F78+F80 -> 123084475
B8: 2 | C8: 46220 | D8: Pembayaran Termin I | E8: 277500000 | G8: =G7+E8 -> 277452000 | I8: Upah Tukang | J8: =F10+SUM(F15:F17)+F19+F26+F28+F32+SUM(F38:F39)+F43+F45+F49+SUM(F54:F56)+SUM(F62:F63)+F66+F71+SUM(F73:F74)+F77+F79+F81 -> 131808350
B9: 3 | C9: 46224 | D9: Bayar Kosan | F9: 800000 | G9: =G8-F9 -> 276652000 | I9: Sewa Alat Proyek | J9: =F35+F67 -> 3796000
B10: 4 | C10: 46224 | D10: Kasbon Mang Rian | F10: 2200000 | G10: =G9-F10 -> 274452000 | I10: Transportasi Lapangan | J10: =F9+F31+F33+F53 -> 2141600
B11: 5 | C11: 46224 | D11: Belanja Material | F11: 4599000 | G11: =G10-F11 -> 269853000 | J11: =SUM(J7:J10) -> 260830425
B12: 6 | C12: 46224 | D12: Uang Satpam | F12: 100000 | G12: =G11-F12 -> 269753000
B13: 7 | C13: 46224 | D13: Belanja Material | F13: 2852000 | G13: =G12-F13 -> 266901000 | I13: Pak Jayadih | J13: =F27+F39+F42+F21 -> 51075375
B14: 8 | C14: 46227 | D14: Belanja Material | F14: 2988000 | G14: =G13-F14 -> 263913000 | I14: Mang Rian | J14: =J8-J13 -> 80732975
B15: 9 | C15: 46228 | D15: Kasbon Mang Rian | F15: 1500000 | G15: =G14-F15 -> 262413000
B16: 10 | C16: 46230 | D16: Gajian Mang Rian | F16: 894350 | G16: =G15-F16 -> 261518650
B17: 11 | C17: 46230 | D17: Kasbon Mang Rian | F17: 1000000 | G17: =G16-F17 -> 260518650
B18: 12 | C18: 46234 | D18: Belanja Material | F18: 3899000 | G18: =G17-F18 -> 256619650
B19: 13 | C19: 46235 | D19: Gajian Mang Rian | F19: 4468750 | G19: =G18-F19 -> 252150900
B20: 13 | C20: 46237 | D20: Belanja Material | F20: 2095000 | G20: =G19-F20 -> 250055900
B21: 14 | C21: 46237 | D21: Belanja Baja | F21: 15075375 | G21: =G20-F21 -> 234980525
B22: 15 | C22: 46239 | D22: Belanja Material | F22: 2913000 | G22: =G21-F22 -> 232067525
B23: 16 | C23: 46239 | D23: Belanja Material | F23: 712500 | G23: =G22-F23 -> 231355025
B24: 17 | C24: 46240 | D24: Belanja Material | F24: 525000 | G24: =G23-F24 -> 230830025
B25: 18 | C25: 46241 | D25: Belanja Material | F25: 1150000 | G25: =G24-F25 -> 229680025
B26: 19 | C26: 46242 | D26: Gajian Mang Rian | F26: 10469000 | G26: =G25-F26 -> 219211025
... B56: 49 | C56: 46276 | D56: Pelunasan Baja Pak Jayadih | F56: 5000000 | G56: =G55-F56 -> 83327325
B57: 50 | C57: 46277 | D57: Pembayaran Termin II | E57: 111000000 | G57: =G56+E57 -> 194327325
B58: 51 | C58: 46279 | D58: Material | F58: 710000 | G58: =G57-F58 -> 193617325
B59: 52 | C59: 46280 | D59: Atap Genteng | F59: 4030000 | G59: =G58-F59 -> 189587325
B60: 53 | C60: 46282 | D60: Material | F60: 1300000 | G60: =G59-F60 -> 188287325
B61: 54 | C61: 46282 | D61: Material Listrik | F61: 765000 | G61: =G60-F61 -> 187522325
B62: 55 | C62: 46283 | D62: Gajian Mang Rian | F62: 11356100 | G62: =G61-F62 -> 176166225
B63: 56 | C63: 46284 | D63: Kasbon Mas Rudy | F63: 2000000 | G63: =G62-F63 -> 174166225
B64: 57 | C64: 46284 | D64: Material | F64: 1956000 | G64: =G63-F64 -> 172210225
B65: 58 | C65: 46286 | D65: Material | F65: 1741000 | G65: =G64-F65 -> 170469225
B66: 59 | C66: 46286 | D66: Kasbon Mang Rian | F66: 1000000 | G66: =G65-F66 -> 169469225
B67: 60 | C67: 46287 | D67: Perpanjang Sewa Scaffolding | F67: 1248000 | G67: =G66-F67 -> 168221225
B68: 61 | C68: 46288 | D68: Material Plafon | F68: 2308000 | G68: =G67-F68 -> 165913225
B69: 62 | C69: 46290 | D69: Material | F69: 620000 | G69: =G68-F69 -> 165293225
... B76: 69 | C76: 46297 | D76: Material | F76: 1050000 | G76: =G75-F76 -> 142220525
B77: 70 | C77: 46297 | D77: Gajian Mang Rian | F77: =8750950+420000+150000 -> 9320950 | G77: =G76-F77 -> 132899575
B78: 71 | C78: 46297 | D78: Buang Puing | F78: 1850000 | G78: =G77-F78 -> 131049575
B79: 72 | C79: 46300 | D79: Kasbon Mang Rian | F79: 1000000 | G79: =G78-F79 -> 130049575
B80: 73 | C80: 46302 | D80: Material | F80: 1880000 | G80: =G79-F80 -> 128169575
B81: 74 | C81: 46302 | D81: Kasbon Mas Rudy | F81: 500000 | G81: =G80-F81 -> 127669575
B82: 75 | C82: 46304 | D82: Gajian Mang Rian | F82: 4875700
B87: Jumlah | E87: =SUM(E7:E86) -> 388500000 | F87: =SUM(F7:F86) -> 265706125 | G87: =E87-F87 -> 122793875
G88: =G87/E87 -> 0.31607175

Sheet DNN Office - Kemayoran
B2: Time Travel Design
B3: DNN Office - Albert Anthonius
B4: Laporan Keuangan
B5: 2026
B6: No | C6: Tanggal | D6: Keterangan | E6: Debit | F6: Kredit | G6: Saldo Akhir | I6: Pengelompokan | J6: Total
B7: 1 | C7: 46182 | D7: Pembayaran Tahap I | E7: 192500000 | G7: =E7 -> 192500000 | I7: Bahan Baku Utama / Material | J7: =SUM(K7:L7) -> 195624426 | K7: =SUM(F9:F17,F19,F23,F25,F27,F29,F31,F32,F34,F36,F38:F39,F41:F50,F52:F55,F57,F60:F74,F76:F77,F80,F82:F90,F92:F95,F98:F101,F104:F106,F108,F110:F111,F113:F117,F119:F121,F123:F125,F129,F131:F141,F143,F145:F152,F155:F157,F160:F162,F165:F169,F171) -> 184308569 | L7: =SUM(F173,F175:F178,F185:F186,F188:F189,F192,F194:F195,F197:F198) -> 11315857
B8: 2 | C8: 46182 | D8: Kasbon Mang Edi | F8: 860000 | G8: =G7-F8 -> 191640000 | I8: Upah Tukang | J8: =F8+F18+F20+F22+F24+F26+F28+F33+F35+F37+F40+F58+SUM(F78:F79)+F81+SUM(F96:F97)+F112+F118+SUM(F126:F128)+F142+F144+SUM(F153:F154)+F158+F174+SUM(F179:F183)+F187+SUM(F190:F191)+F193+F196 -> 157008500
B9: 3 | C9: 46183 | D9: Print Invoice | F9: 3000 | G9: =G8-F9 -> 191637000 | I9: Sewa Alat Proyek
B10: 4 | C10: 46185 | D10: Perintilan Pembongkaran | F10: 58000 | G10: =G9-F10 -> 191579000 | I10: Transportasi Lapangan | J10: =F21+F30+F51+F56+F59+F75+F91+SUM(F102:F103,F109)+F122+F130+F159+SUM(F163:F164)+F170 -> 2471000
B11: 5 | C11: 46185 | D11: Print dan Materai | F11: 31000 | G11: =G10-F11 -> 191548000 | J11: =SUM(J7:J10) -> 355103926
B12: 6 | C12: 46190 | D12: Belanja Material | F12: 917500 | G12: =G11-F12 -> 190630500
B13: 7 | C13: 46191 | D13: Belanja Karung | F13: 140000 | G13: =G12-F13 -> 190490500 | I13: Total Kasbon Mas Imam | J13: =F78+F96+F112+F126+F144+F158+F174+F180+F190+F193+F196 -> 60000000
B14: 8 | C14: 46192 | D14: Buang Puing | F14: 350000 | G14: =G13-F14 -> 190140500 | I14: Sisa Kasbon Mas Imam | J14: =(37000000+18000000+3000000+2000000)-J13 -> 0
B15: 9 | C15: 46193 | D15: Belanja Material | F15: 437500 | G15: =G14-F15 -> 189703000
B16: 10 | C16: 46193 | D16: Buang Puing | F16: 700000 | G16: =G15-F16 -> 189003000
B17: 11 | C17: 46193 | D17: Parkir, Print Gambar dan Perintilan | F17: 178000 | G17: =G16-F17 -> 188825000
B18: 12 | C18: 46193 | D18: Gajian Mang Edi | F18: 3200000 | G18: =G17-F18 -> 185625000
B19: 13 | C19: 46194 | D19: Belanja Baja Ringan | F19: 1570000 | G19: =G18-F19 -> 184055000
B20: 14 | C20: 46195 | D20: Kasbon Mang Edi | F20: 500000 | G20: =G19-F20 -> 183555000
B21: 15 | C21: 46196 | D21: Pindahan Barang Bongkaran | F21: 244000 | G21: =G20-F21 -> 183311000
B22: 16 | C22: 46197 | D22: Kasbon Mang Edi | F22: 1000000 | G22: =G21-F22 -> 182311000
B23: 17 | C23: 46198 | D23: Gypsum dan Baja Ringan | F23: 6670000 | G23: =G22-F23 -> 175641000
B24: 18 | C24: 45835 | D24: Gajian Tukang Pindahan Bongkaran | F24: 260000 | G24: =G23-F24 -> 175381000
B25: 19 | C25: 45835 | D25: Bon Belanjaan | F25: 367000 | G25: =G24-F25 -> 175014000
B26: 20 | C26: 45835 | D26: Gajian Mang Edi | F26: 5365000 | G26: =G25-F26 -> 169649000
... B106: 100 | C106: 46238 | D106: Lalamove Interior | F106: 550000 | G106: =G105-F106 -> -27459198
B107: 101 | C107: 46238 | D107: Pembayaran Termin II | E107: 77000000 | G107: =G106+E107 -> 49540802
B108: 102 | C108: 46238 | D108: Buang Puing | F108: 500000 | G108: =G107-F108 -> 49040802
B109: 103 | C109: 46238 | D109: Lalamove LED Strip | F109: 45000 | G109: =G108-F109 -> 48995802
B110: 104 | C110: 46238 | D110: Stop Kontak Lantai | F110: 493600 | G110: =G109-F110 -> 48502202
B111: 105 | C111: 46238 | D111: Cat Oplos | F111: 274000 | G111: =G110-F111 -> 48228202
B112: 106 | C112: 46238 | D112: Kasbon Mas Imam | F112: 1500000 | G112: =G111-F112 -> 46728202
B113: 107 | C113: 46238 | D113: Sealent | F113: 370000 | G113: =G112-F113 -> 46358202
B114: 108 | C114: 46239 | D114: Poles Lantai Kantor | F114: 2700000 | G114: =G113-F114 -> 43658202
B115: 109 | C115: 46240 | D115: Belanja Material | F115: 1086000 | G115: =G114-F115 -> 42572202
B116: 110 | C116: 46240 | D116: Belanja Material | F116: 1340000 | G116: =G115-F116 -> 41232202
B117: 111 | C117: 46240 | D117: Belanja WPC | F117: 1900000 | G117: =G116-F117 -> 39332202
B118: 112 | C118: 46240 | D118: Kasbon Mang Edi | F118: 1002500 | G118: =G117-F118 -> 38329702
B119: 113 | C119: 46241 | D119: Belanja Material | F119: 195000 | G119: =G118-F119 -> 38134702
... B171: 165 | C171: 46259 | D171: Perintilan Sink | F171: 105000 | G171: =G170-F171 -> -51822069
B172: 166 | C172: 46229 | D172: Pembayaran Termin III | E172: 77000000 | G172: =G171+E172 -> 25177931
B173: 167 | C173: 46260 | D173: Stiker Logo | F173: 100000 | G173: =G172-F173 -> 25077931
B174: 168 | C174: 46261 | D174: Kasbon Mas Imam | F174: 8000000 | G174: =G173-F174 -> 17077931
B175: 169 | C175: 46262 | D175: Lampu Kantor | F175: 646999 | G175: =G174-F175 -> 16430932
B176: 170 | C176: 46263 | D176: Resin dan Cat | F176: 184900 | G176: =G175-F176 -> 16246032
B177: 171 | C177: 46263 | D177: Material | F177: 2589000 | G177: =G176-F177 -> 13657032
B178: 172 | C178: 46269 | D178: Kupas Lantai | F178: 1800000 | G178: =G177-F178 -> 11857032
B179: 173 | C179: 46269 | D179: Tips Mas Iwan | F179: 200000 | G179: =G178-F179 -> 11657032
B180: 174 | C180: 46270 | D180: Kasbon Mas Imam | F180: 2500000 | G180: =G179-F180 -> 9157032
B181: 175 | C181: 46270 | D181: Gajian Mang Rian | F181: 5000000 | G181: =G180-F181 -> 4157032
B182: 176 | C182: 46271 | D182: Kasbon Mang Rian | F182: 500000 | G182: =G181-F182 -> 3657032
B183: 177 | C183: 46273 | D183: Borongan Lantai Mang Rian | F183: 2150000 | G183: =G182-F183 -> 1507032
B184: 178 | C184: 46275 | D184: Pembayaran Pelunasan Awal | E184: 73738182 | G184: =G183+E184 -> 75245214
B185: 179 | C185: 46276 | D185: Gantungan Lampu | F185: 332758 | G185: =G184-F185 -> 74912456
B186: 180 | C186: 46277 | D186: Material | F186: 255000 | G186: =G185-F186 -> 74657456
B187: 181 | C187: 46277 | D187: Gajian Mang Edi | F187: 396000 | G187: =G186-F187 -> 74261456
B188: 182 | C188: 46277 | D188: Lampu LED Strip | F188: 487000 | G188: =G187-F188 -> 73774456
B189: 183 | C189: 46278 | D189: Backdrop Concrete Panel | F189: 3000000 | G189: =G188-F189 -> 70774456
B190: 184 | C190: 46283 | D190: Kasbon Mas Imam | F190: 1500000 | G190: =G189-F190 -> 69274456
B191: 185 | C191: 46283 | D191: Gajian Mang Edi | F191: 720000 | G191: =G190-F191 -> 68554456
B192: 186 | C192: 46287 | D192: Lem Wallpanel | F192: 192000 | G192: =G191-F192 -> 68362456
B193: 187 | C193: 46287 | D193: Kasbon Mas Imam | F193: 500000 | G193: =G192-F193 -> 67862456
B194: 188 | C194: 46287 | D194: Wallpanel Tambahan | F194: 604200 | G194: =G193-F194 -> 67258256
B195: 189 | C195: 46288 | D195: Lem Wallpanel | F195: 174000 | G195: =G194-F195 -> 67084256
B196: 190 | C196: 46290 | D196: Kasbon Mas Imam | F196: 1000000 | G196: =G195-F196 -> 66084256
... B198: 192 | C198: 46300 | D198: SPC Ganti | F198: 835000 | G198: =G197-F198 -> 65134256
B199: 193 | C199: 46304 | D199: Oplos Cat | F199: 145000
B200: 194 | C200: 46304 | D200: Material | F200: 528000
B205: Jumlah | E205: =SUM(E7:E204) -> 420238182 | F205: =SUM(F7:F204) -> 355776926 | G205: =E205-F205 -> 64461256
G206: =G205/E205 -> 0.15339219

Sheet RM Kost - Epi Suryadinata
B2: Time Travel Design
B3: RM Kost - Epi Suryadinata
B4: Laporan Keuangan
B5: 2026
B6: No | C6: Tanggal | D6: Keterangan | E6: Debit | F6: Kredit | G6: Saldo Akhir | I6: Pengelompokan | J6: Total
B7: 1 | C7: 46142 | D7: Print Kontrak dan Materai | F7: 36000 | G7: =-F7 -> -36000 | I7: Bahan Baku Utama / Material | J7: =F7+F12+SUM(F15:F20)+SUM(F22:F28)+F31+F33+SUM(F35:F39)+SUM(F41:F42)+SUM(F44:F49)+SUM(F51:F54)+SUM(F57:F60)+SUM(F62:F63)+SUM(F65:F67)+SUM(F69:F71)+SUM(F73:F78)+SUM(F82:F84)+SUM(F86:F87)+SUM(F89:F90)+F92+SUM(F94:F98)+F100+SUM(F102:F104)+SUM(F107:F108)+SUM(F111:F114,F116:F118) -> 171426833
B8: 2 | C8: 46146 | D8: Pembayaran Termin I (Tahap I) | E8: 50000000 | G8: =G7+E8 -> 49964000 | I8: Upah Tukang | J8: =F13+F21+F29+F30+F32+F34+F40+F43+F50+SUM(F55:F56)+F61+F64+F68+F72+SUM(F79:F80)+F85+F88+F91+F93+F99+F101+SUM(F105:F106)+SUM(F109:F110)+F115 -> 148753670
B9: 3 | C9: 46147 | D9: Pembayaran Termin I (Tahap II) | E9: 50000000 | G9: =G8+E9 -> 99964000 | I9: Sewa Alat Proyek
B10: 4 | C10: 46148 | D10: Pembayaran Termin I (Tahap III) | E10: 50000000 | G10: =G9+E10 -> 149964000 | I10: Transportasi Lapangan
B11: 5 | C11: 46149 | D11: Pembayaran Termin I (Tahap IV) | E11: 50000000 | G11: =G10+E11 -> 199964000 | J11: =SUM(J7:J10) -> 320180503
B12: 6 | C12: 46150 | D12: Belanja Hebel dan Pasir Semen | F12: 3892000 | G12: =G11-F12 -> 196072000
B13: 7 | C13: 46150 | D13: Kasbon Mang Rian | F13: 2000000 | G13: =G12-F13 -> 194072000 | I13: Borongan Mas Imam | J13: 7800000
B14: 8 | C14: 46150 | D14: Pembayaran Termin I (Tahap V) | E14: 100000000 | G14: =G13+E14 -> 294072000 | I14: Kasbon Mas Imam | J14: =F106+F109 -> 5500000
B15: 9 | C15: 46151 | D15: Gali Bor Sumur | F15: 6002500 | G15: =G14-F15 -> 288069500 | I15: Sisa Borongan Mas Imam | J15: =J13-J14 -> 2300000
B16: 10 | C16: 46153 | D16: Belanja Perintilan | F16: 625000 | G16: =G15-F16 -> 287444500
B17: 11 | C17: 46154 | D17: Belanja Kolom Praktis | F17: 1050000 | G17: =G16-F17 -> 286394500
B18: 12 | C18: 46154 | D18: Buang Puing | F18: 350000 | G18: =G17-F18 -> 286044500
B19: 13 | C19: 46156 | D19: Belanja Hebel dan Besi | F19: 1985000 | G19: =G18-F19 -> 284059500
B20: 14 | C20: 46156 | D20: Belanja Ring Besi | F20: 345000 | G20: =G19-F20 -> 283714500
B21: 15 | C21: 46157 | D21: Borongan Mang Rian | F21: 5500000 | G21: =G20-F21 -> 278214500
B22: 16 | C22: 46158 | D22: Belanja Hebel dan Mortar | F22: 2070000 | G22: =G21-F22 -> 276144500
B23: 17 | C23: 46160 | D23: Buang Puing | F23: 350000 | G23: =G22-F23 -> 275794500
B24: 18 | C24: 46161 | D24: Belanja Bon Mang Rian | F24: 485000 | G24: =G23-F24 -> 275309500
B25: 19 | C25: 46162 | D25: Belanja Hebel dan Pasir Semen | F25: 2525000 | G25: =G24-F25 -> 272784500
B26: 20 | C26: 46163 | D26: Buang Puing | F26: 350000 | G26: =G25-F26 -> 272434500
B27: 21 | C27: 46164 | D27: Buang Puing | F27: 350000 | G27: =G26-F27 -> 272084500
... B80: 74 | C80: 46242 | D80: Kasbon Listrik Mas Aris | F80: 3000000 | G80: =G79-F80 -> 89965682
B81: 75 | C81: 46244 | D81: Pembayaran Termin Kedua | E81: 150000000 | G81: =G80+E81 -> 239965682
B82: 76 | C82: 46244 | D82: Belanja Material | F82: 799000 | G82: =G81-F82 -> 239166682
B83: 77 | C83: 46245 | D83: Belanja Material | F83: 285000 | G83: =G82-F83 -> 238881682
B84: 78 | C84: 46246 | D84: Belanjaan Plafon | F84: 6500000 | G84: =G83-F84 -> 232381682
B85: 79 | C85: 46248 | D85: Gajian Mang Rian | F85: 6448000 | G85: =G84-F85 -> 225933682
B86: 80 | C86: 46248 | D86: Belanja Material | F86: 1195000 | G86: =G85-F86 -> 224738682
B87: 81 | C87: 46249 | D87: Belanja Material | F87: 1195000 | G87: =G86-F87 -> 223543682
B88: 82 | C88: 46255 | D88: Gajian Mang Rian | F88: 6200000 | G88: =G87-F88 -> 217343682
B89: 83 | C89: 46258 | D89: Belanja Material | F89: 1707000 | G89: =G88-F89 -> 215636682
B90: 84 | C90: 46261 | D90: Beli Keramik | F90: 12871340 | G90: =G89-F90 -> 202765342
B91: 85 | C91: 46262 | D91: Gajian Mang Rian | F91: 12600000 | G91: =G90-F91 -> 190165342
B92: 86 | C92: 46268 | D92: Penambahan Keramik | F92: 686045 | G92: =G91-F92 -> 189479297
B93: 87 | C93: 46270 | D93: Gajian Mang Rian | F93: 2592000 | G93: =G92-F93 -> 186887297
... B118: 112 | C118: 46303 | D118: Material | F118: 215000 | G118: =G117-F118 -> 129819497
B119: 113 | C119: 46304 | D119: Gajian Mang Rian | F119: 3600800
B120: 114 | C120: 46304 | D120: Kasbon Mas Imam | F120: 1500000
B121: 115 | C121: 46305 | D121: Material | F121: 1722000
B126: Jumlah | E126: =SUM(E7:E125) -> 450000000 | F126: =SUM(F7:F125) -> 327003303 | G126: =E126-F126 -> 122996697

Sheet SJ House - Tria Andika (KM)
B2: Time Travel Design
B3: SJ House - Tria Andika (KM)
B4: Laporan Keuangan
B5: 2026
B6: No | C6: Tanggal | D6: Keterangan | E6: Debit | F6: Kredit | G6: Saldo Akhir | I6: Pengelompokan | J6: Total
B7: 1 | C7: 46265 | D7: Kosan Tukang | F7: 1100000 | G7: =-F7 -> -1100000 | I7: Bahan Baku Utama / Material | J7: =SUM(F10:F15)+SUM(F18:F19,F21)+SUM(F23:F27)+SUM(F30:F32)+F34+SUM(F36:F38)+SUM(F41:F45) -> 34348151
B8: 2 | C8: 46267 | D8: Pembayaran Pelunasan | E8: 58000000 | G8: =G7+E8 -> 56900000 | I8: Upah Tukang | J8: =F9+SUM(F16:F17)+F20+SUM(F28:F29)+F33+F35+SUM(F39:F40) -> 13524000
B9: 3 | C9: 46272 | D9: Kasbon Mang Edi | F9: 500000 | G9: =G8-F9 -> 56400000 | I9: Sewa Alat Proyek
B10: 4 | C10: 46272 | D10: Material | F10: 130000 | G10: =G9-F10 -> 56270000 | I10: Transportasi Lapangan | J10: =F7+F22 -> 1350000
B11: 5 | C11: 46273 | D11: Material Interior | F11: 1795500 | G11: =G10-F11 -> 54474500 | J11: =SUM(J7:J10) -> 49222151
B12: 6 | C12: 46273 | D12: Material Plafon | F12: 907000 | G12: =G11-F12 -> 53567500
B13: 7 | C13: 46273 | D13: Keramik Kamar Mandi | F13: 1525500 | G13: =G12-F13 -> 52042000 | I13: Kasbon Mas Imam | J13: =F16+F28 -> 4000000
B14: 8 | C14: 46275 | D14: Material | F14: 300000 | G14: =G13-F14 -> 51742000 | I14: Sisa Kasbon Mas Imam | J14: =5500000-J13 -> 1500000
B15: 9 | C15: 46276 | D15: HPL Interior | F15: 840000 | G15: =G14-F15 -> 50902000
B16: 10 | C16: 46276 | D16: Kasbon Mas Imam | F16: 2500000 | G16: =G15-F16 -> 48402000
B17: 11 | C17: 46277 | D17: Gajian Mang Edi | F17: 1770000 | G17: =G16-F17 -> 46632000
B18: 12 | C18: 46278 | D18: Kloset | F18: 7107734 | G18: =G17-F18 -> 39524266
B19: 13 | C19: 46279 | D19: Engsel Interior | F19: 390000 | G19: =G18-F19 -> 39134266
B20: 14 | C20: 46279 | D20: Kasbon Mang Edi | F20: 500000 | G20: =G19-F20 -> 38634266
B21: 15 | C21: 46279 | D21: Material | F21: 200000 | G21: =G20-F21 -> 38434266
B22: 16 | C22: 46281 | D22: Lalamove Interior | F22: 250000 | G22: =G21-F22 -> 38184266
B23: 17 | C23: 46281 | D23: Material | F23: 255000 | G23: =G22-F23 -> 37929266
B24: 18 | C24: 46281 | D24: Keramik Kamar Mandi | F24: 344000 | G24: =G23-F24 -> 37585266
B25: 19 | C25: 46281 | D25: Engsel | F25: 100000 | G25: =G24-F25 -> 37485266
B26: 20 | C26: 46282 | D26: Keramik Dinding Kamar Mandi | F26: 915000 | G26: =G25-F26 -> 36570266
... B45: 39 | C45: 46297 | D45: Lalamove Keramik | F45: 95000 | G45: =G44-F45 -> 8777849
B46: Jumlah | E46: =SUM(E7:E44) -> 58000000 | F46: =SUM(F7:F45) -> 49222151 | G46: =E46-F46 -> 8777849
G47: =G46/E46 -> 0.15134222

Sheet Dapur Bebek - Bintaro
B2: Time Travel Design
B3: Dapur Bebek Bu Enno - Bintaro
B4: Laporan Keuangan
B5: 2026
B6: No | C6: Tanggal | D6: Keterangan | E6: Debit | F6: Kredit | G6: Saldo Akhir | I6: Pengelompokan | J6: Total
B7: 1 | C7: 46216 | D7: Pembayaran Tahap I | E7: 41250000 | G7: =E7 -> 41250000 | I7: Bahan Baku Utama / Material | J7: =SUM(F10:F12,F14:F20,F23,F25:F29,F31:F32,F34:F35,F37:F38,F40:F42,F44:F47,F49:F59,F61,F63:F68,F70:F72,F77:F78,F82:F83) -> 54589797
B8: 2 | C8: 46216 | D8: Kasbon Mang Rian | F8: 2000000 | G8: =G7-F8 -> 39250000 | I8: Upah Tukang | J8: =F8+F13+SUM(F21:F22)+F24+F30+F33+F39+F43+F48+F60+F62+SUM(F74:F75)+SUM(F80:F81)+F84 -> 50119400
B9: 3 | C9: 46216 | D9: Bayar Ormas | F9: 1500000 | G9: =G8-F9 -> 37750000 | I9: Sewa Alat Proyek
B10: 4 | C10: 46217 | D10: Print Kontrak | F10: 58000 | G10: =G9-F10 -> 37692000 | I10: Transportasi Lapangan | J10: =F9+F69+F73 -> 1850000
B11: 5 | C11: 46218 | D11: Buang Sampah | F11: 1600000 | G11: =G10-F11 -> 36092000 | J11: =SUM(J7:J10) -> 106559197
B12: 6 | C12: 46219 | D12: Belanja Material | F12: 2667500 | G12: =G11-F12 -> 33424500
B13: 7 | C13: 46221 | D13: Gajian Mang Rian | F13: =561950+1180000+200000 -> 1941950 | G13: =G12-F13 -> 31482550 | I13: Kasbon Mas Imam | J13: =F60+F74 -> 5000000
B14: 8 | C14: 46221 | D14: Belanja Material | F14: 681500 | G14: =G13-F14 -> 30801050 | I14: Sisa Kasbon Mas Imam | J14: =5000000-J13 -> 0
B15: 9 | C15: 46221 | D15: Upah Bongkar Kaca | F15: 1050000 | G15: =G14-F15 -> 29751050
B16: 10 | C16: 46223 | D16: Belanja Material | F16: 1630000 | G16: =G15-F16 -> 28121050
B17: 11 | C17: 46223 | D17: Belanja Perintilan | F17: 190000 | G17: =G16-F17 -> 27931050
B18: 12 | C18: 46224 | D18: Belanja Material | F18: 926500 | G18: =G17-F18 -> 27004550
B19: 13 | C19: 46226 | D19: Belanja Material | F19: 1034500 | G19: =G18-F19 -> 25970050
B20: 14 | C20: 46228 | D20: Belanja Material | F20: 1172000 | G20: =G19-F20 -> 24798050
B21: 15 | C21: 46228 | D21: Gajian Mang Rian | F21: 4377450 | G21: =G20-F21 -> 20420600
B22: 16 | C22: 46230 | D22: Kasbon Mas Aris Listrik | F22: 1000000 | G22: =G21-F22 -> 19420600
B23: 17 | C23: 46234 | D23: Belanja Material | F23: 1187000 | G23: =G22-F23 -> 18233600
B24: 18 | C24: 46235 | D24: Gajian Mang Rian | F24: 5300000 | G24: =G23-F24 -> 12933600
B25: 19 | C25: 46237 | D25: Belanja Material | F25: 657000 | G25: =G24-F25 -> 12276600
B26: 20 | C26: 46238 | D26: Belanjaan Keramik | F26: 990000 | G26: =G25-F26 -> 11286600
... B35: 29 | C35: 46248 | D35: Pelunasan Besi Bintaro | F35: 2002500 | G35: =G34-F35 -> -15213394
B36: 30 | C36: 46248 | D36: Pembayaran Tahap II | E36: 20625000 | G36: =G35+E36 -> 5411606
B37: 31 | C37: 46249 | D37: Belanja Material | F37: 1325000 | G37: =G36-F37 -> 4086606
B38: 32 | C38: 46249 | D38: Belanja Keramik | F38: 115000 | G38: =G37-F38 -> 3971606
B39: 33 | C39: 46249 | D39: Kasbon Mas Aris Listrik | F39: 2000000 | G39: =G38-F39 -> 1971606
B40: 34 | C40: 46250 | D40: Belanja Cat | F40: 1855000 | G40: =G39-F40 -> 116606
B41: 35 | C41: 46253 | D41: Belanja Material | F41: 1493000 | G41: =G40-F41 -> -1376394
B42: 36 | C42: 46253 | D42: Belanja Material | F42: 596000 | G42: =G41-F42 -> -1972394
B43: 37 | C43: 46255 | D43: Gajian Mang Rian | F43: 7300000 | G43: =G42-F43 -> -9272394
B44: 38 | C44: 46256 | D44: Belanja Material | F44: 908000 | G44: =G43-F44 -> -10180394
B45: 39 | C45: 46258 | D45: Belanja Material | F45: 360000 | G45: =G44-F45 -> -10540394
B46: 40 | C46: 46260 | D46: Bahan Interior | F46: 1180000 | G46: =G45-F46 -> -11720394
B47: 41 | C47: 46261 | D47: Listrik Bintaro | F47: 806500 | G47: =G46-F47 -> -12526894
B48: 42 | C48: 46262 | D48: Gajian Mang Rian | F48: 5500000 | G48: =G47-F48 -> -18026894
... B75: 70 | C75: 46277 | D75: Gajian Mang Edi | F75: 780000 | G75: =G74-F75 -> -39597933
B76: 71 | C76: 46278 | D76: Fee Pemasangan Gas | E76: 2000000 | G76: =G75+E76 -> -37597933
B77: 72 | C77: 46278 | D77: Pelunasan Besi Bintaro | F77: 502500 | G77: =G76-F77 -> -38100433
B78: 73 | C78: 46280 | D78: Exhaust | F78: 363764 | G78: =G77-F78 -> -38464197
B79: 74 | C79: 46281 | D79: Pembayaran Pelunasan | E79: 33800000 | G79: =G78+E79 -> -4664197
B80: 75 | C80: 46281 | D80: Pelunasan Mas Imam | F80: 1000000 | G80: =G79-F80 -> -5664197
B81: 76 | C81: 46281 | D81: Pelunasan Mas Aris | F81: 2000000 | G81: =G80-F81 -> -7664197
B82: 77 | C82: 46281 | D82: Material Cat | F82: 200000 | G82: =G81-F82 -> -7864197
B83: 78 | C83: 46283 | D83: Material dan Transport | F83: 300000 | G83: =G82-F83 -> -8164197
B84: 79 | C84: 46283 | D84: Gajian Mang Edi | F84: 720000 | G84: =G83-F84 -> -8884197
B85: Jumlah | E85: =SUM(E7:E84) -> 97675000 | F85: =SUM(F7:F84) -> 106559197 | G85: =E85-F85 -> -8884197

Sheet SJ House - Tria Andika (LT 3)
B2: Time Travel Design
B3: SJ House - Tria Andika (LT 3)
B4: Laporan Keuangan
B5: 2026
B6: No | C6: Tanggal | D6: Keterangan | E6: Debit | F6: Kredit | G6: Saldo Akhir | I6: Pengelompokan | J6: Total
B7: 1 | C7: 46223 | D7: Belanja Cat | F7: 485769 | G7: =-F7 -> -485769 | I7: Bahan Baku Utama / Material | J7: =F7+F8+SUM(F12:F14)+F16+SUM(F18:F22)+SUM(F24:F25)+F28+F31+SUM(F33:F35)+SUM(F39:F40,F42) -> 22743524
B8: 2 | C8: 46223 | D8: Belanja Material | F8: 1214000 | G8: =G7-F8 -> -1699769 | I8: Upah Tukang | J8: =F10+F15+F17+F23+SUM(F26:F27)+F29+F36+F38+F43 -> 18725000
B9: 3 | C9: 46223 | D9: Kosan Tukang | F9: 1100000 | G9: =G8-F9 -> -2799769 | I9: Sewa Alat Proyek
B10: 4 | C10: 46225 | D10: Kasbon Mang Edi | F10: 2002500 | G10: =G9-F10 -> -4802269 | I10: Transportasi Lapangan | J10: =F9+F30+F32+F37 -> 1725000
B11: 5 | C11: 46226 | D11: Pembayaran Pelunasan | E11: 45000000 | G11: =G10+E11 -> 40197731 | J11: =SUM(J7:J10) -> 43193524
B12: 6 | C12: 46226 | D12: Belanja Bahan | F12: 533000 | G12: =G11-F12 -> 39664731
B13: 7 | C13: 46227 | D13: Belanja List Gypsum | F13: 170000 | G13: =G12-F13 -> 39494731
B14: 8 | C14: 46227 | D14: Belanja Cat Plafon | F14: 619000 | G14: =G13-F14 -> 38875731
B15: 9 | C15: 46228 | D15: Gajian Mang Edi | F15: 2162500 | G15: =G14-F15 -> 36713231
B16: 10 | C16: 46233 | D16: Belanja Material | F16: 2202000 | G16: =G15-F16 -> 34511231
B17: 11 | C17: 46235 | D17: Gajian Mang Edi | F17: 2382500 | G17: =G16-F17 -> 32128731
B18: 12 | C18: 46237 | D18: Belanja LED Strip | F18: 873525 | G18: =G17-F18 -> 31255206
B19: 13 | C19: 46237 | D19: DP Roster | F19: 200000 | G19: =G18-F19 -> 31055206
B20: 14 | C20: 46238 | D20: Belanja Material | F20: 1489000 | G20: =G19-F20 -> 29566206
B21: 15 | C21: 46238 | D21: Pelunasan Roster | F21: 3052500 | G21: =G20-F21 -> 26513706
B22: 16 | C22: 46241 | D22: Belanja Material | F22: 501000 | G22: =G21-F22 -> 26012706
B23: 17 | C23: 46242 | D23: Gajian Mang Edi | F23: 2492500 | G23: =G22-F23 -> 23520206
... B40: 34 | C40: 46267 | D40: Cat Dinding | F40: 763000 | G40: =G39-F40 -> 4275476
B41: 35 | C41: 46267 | D41: Pembayaran Pelunasan | E41: 2000000 | G41: =G40+E41 -> 6275476
B42: 36 | C42: 46268 | D42: Material | F42: 344000 | G42: =G41-F42 -> 5931476
B43: 37 | C43: 46269 | D43: Gajian Mang Edi | F43: 2125000 | G43: =G42-F43 -> 3806476
B44: Jumlah | E44: =SUM(E7:E43) -> 47000000 | F44: =SUM(F7:F43) -> 43193524 | G44: =E44-F44 -> 3806476
G45: =G44/E44 -> 0.080988851

Sheet Kantor Blok SR - Kemayoran
B2: Time Travel Design
B3: Kantor Blok SR - Kemayoran
B4: Laporan Keuangan
B5: 2026
B6: No | C6: Tanggal | D6: Keterangan | E6: Debit | F6: Kredit | G6: Saldo Akhir | I6: Pengelompokan | J6: Total
B7: 1 | C7: 46207 | D7: Beli Bahan Cat | F7: 399000 | G7: =-F7 -> -399000 | I7: Bahan Baku Utama / Material | J7: =SUM(F7:F8)+SUM(F10:F11) -> 2232245
B8: 2 | C8: 46208 | D8: Beli Siku Alumunium | F8: 1128305 | G8: =G7-F8 -> -1527305 | I8: Upah Tukang | J8: =F9+F12 -> 1345000
B9: 3 | C9: 46209 | D9: Gajian Mang Edi | F9: 625000 | G9: =G8-F9 -> -2152305 | I9: Sewa Alat Proyek
B10: 4 | C10: 46212 | D10: Lem dan Sealent | F10: 355000 | G10: =G9-F10 -> -2507305 | I10: Transportasi Lapangan
B11: 5 | C11: 46213 | D11: Tambahan Siku Alumunium | F11: 349940 | G11: =G10-F11 -> -2857245 | J11: =SUM(J7:J10) -> 3577245
B12: 6 | C12: 46217 | D12: Gajian Mang Edi | F12: 720000 | G12: =G11-F12 -> -3577245
B13: 7 | C13: 46240 | D13: Pembayaran Pelunasan | E13: 6337500
B14: Jumlah | E14: =SUM(E7:E13) -> 6337500 | F14: =SUM(F7:F13) -> 3577245 | G14: =E14-F14 -> 2760255
G15: =G14/E14 -> 0.4355432

Sheet TJ House - Tommy Saputra (T3)
B2: Time Travel Design
B3: TJ House - Tommy Saputra (T3)
B4: Laporan Keuangan
B5: 2026
B6: No | C6: Tanggal | D6: Keterangan | E6: Debit | F6: Kredit | G6: Saldo Akhir | I6: Pengelompokan | J6: Total
B7: 1 | C7: 46187 | D7: Print Kontrak dan Materai | F7: 33000 | G7: =-F7 -> -33000 | I7: Bahan Baku Utama / Material | J7: =F7+SUM(F12:F13)+F10+F15+F17+SUM(F20:F25)+F27+SUM(F29:F33)+SUM(F36:F40)+SUM(F43:F45)+SUM(F48:F49)+SUM(F52:F56)+SUM(F58:F64) -> 31804249
B8: 2 | C8: 46187 | D8: Grab Mang Edi | F8: 180000 | G8: =G7-F8 -> -213000 | I8: Upah Tukang | J8: =F11+F16+SUM(F18:F19)+F26+SUM(F34:F35)+F41+SUM(F46:F47)+F57+F65 -> 20550000
B9: 3 | C9: 46188 | D9: Pembayaran Tahap I | E9: 38000000 | G9: =G8+E9 -> 37787000 | I9: Sewa Alat Proyek
B10: 4 | C10: 46188 | D10: Belanja Material | F10: 1658000 | G10: =G9-F10 -> 36129000 | I10: Transportasi Lapangan | J10: =F8+F14+F28+F42+F51 -> 1892500
B11: 5 | C11: 46189 | D11: Kasbon Mang Edi | F11: 1500000 | G11: =G10-F11 -> 34629000 | J11: =SUM(J7:J10) -> 54246749
B12: 6 | C12: 46190 | D12: Belanja Material | F12: 545000 | G12: =G11-F12 -> 34084000
B13: 7 | C13: 46190 | D13: Belanja Material | F13: 310000 | G13: =G12-F13 -> 33774000
B14: 8 | C14: 46190 | D14: Perpanjang Kontrakan | F14: 1100000 | G14: =G13-F14 -> 32674000
B15: 9 | C15: 46192 | D15: Belanja Material Interior | F15: 3589000 | G15: =G14-F15 -> 29085000
B16: 10 | C16: 46192 | D16: Kasbon Mas Imam | F16: 500000 | G16: =G15-F16 -> 28585000
B17: 11 | C17: 46193 | D17: DP Kanopi | F17: 3000000 | G17: =G16-F17 -> 25585000
B18: 12 | C18: 46193 | D18: Gajian Mang Edi | F18: 1000000 | G18: =G17-F18 -> 24585000
B19: 13 | C19: 46193 | D19: Kasbon Mas Imam | F19: 1500000 | G19: =G18-F19 -> 23085000
B20: 14 | C20: 46194 | D20: Triplek Pak Indra | F20: 600000 | G20: =G19-F20 -> 22485000
B21: 15 | C21: 46195 | D21: Belanja HPL | F21: 390000 | G21: =G20-F21 -> 22095000
B22: 16 | C22: 46195 | D22: Belanja HPL | F22: 2963000 | G22: =G21-F22 -> 19132000
B23: 17 | C23: 46195 | D23: Belanja SPC | F23: 1584000 | G23: =G22-F23 -> 17548000
... B49: 43 | C49: 46209 | D49: Pintu Alumunium Kaca | F49: 1490000 | G49: =G48-F49 -> -8621544
B50: 44 | C50: 46209 | D50: Pembayaran Tahap II | E50: 19000000 | G50: =G49+E50 -> 10378456
B51: 45 | C51: 46209 | D51: Grab Mas Imam | F51: 126500 | G51: =G50-F51 -> 10251956
B52: 46 | C52: 46210 | D52: Wall Mounted Lamp | F52: 358000 | G52: =G51-F52 -> 9893956
B53: 47 | C53: 46210 | D53: Keramik Top Table Dapur | F53: 168000 | G53: =G52-F53 -> 9725956
B54: 48 | C54: 46210 | D54: Belanja Perintilian | F54: 100000 | G54: =G53-F54 -> 9625956
B55: 49 | C55: 46210 | D55: PVC Sheet | F55: 300000 | G55: =G54-F55 -> 9325956
B56: 50 | C56: 46211 | D56: Akrilik Susu | F56: 15000 | G56: =G55-F56 -> 9310956
B57: 51 | C57: 46211 | D57: Pelunasan Mas Imam + Bonus | F57: 1200000 | G57: =G56-F57 -> 8110956
B58: 52 | C58: 46211 | D58: Pelunasan Kanopi | F58: 1500000 | G58: =G57-F58 -> 6610956
B59: 53 | C59: 46212 | D59: Kawat Nyamuk | F59: 112000 | G59: =G58-F59 -> 6498956
B60: 54 | C60: 46212 | D60: Tambahan Upah Kanopi | F60: 1775000 | G60: =G59-F60 -> 4723956
B61: 55 | C61: 46213 | D61: Hollow dan Pilox | F61: 117000 | G61: =G60-F61 -> 4606956
B62: 56 | C62: 46213 | D62: Keramik Dapur | F62: 168480 | G62: =G61-F62 -> 4438476
... B65: 59 | C65: 46217 | D65: Gajian Mang Edi | F65: 1435000 | G65: =G64-F65 -> 2753251
B66: 60 | C66: 46224 | D66: Pembayaran Pelunasan | E66: 19000000 | G66: =G65+E66 -> 21753251
B67: Jumlah | E67: =SUM(E7:E66) -> 76000000 | F67: =SUM(F7:F66) -> 54246749 | G67: =E67-F67 -> 21753251
G68: =G67/E67 -> 0.28622699

Sheet SJ House - Tria Andika (LT2)
B2: Time Travel Design
B3: SJ House - Tria Andika
B4: Laporan Keuangan
B5: 2026
B6: No | C6: Tanggal | D6: Keterangan | E6: Debit | F6: Kredit | G6: Saldo Akhir | I6: Pengelompokan | J6: Total
B7: 1 | C7: 46160 | D7: Pembayaran Pelunasan | E7: 51000000 | G7: =E7 -> 51000000 | I7: Bahan Baku Utama / Material | J7: =SUM(F8:F19)+SUM(F21:F22)+F24+SUM(F26:F27)+SUM(F29:F30)+SUM(F34:F36)+SUM(F38:F38)+F40+F43+F45+SUM(F50:F51) -> 17453043
B8: 2 | C8: 46160 | D8: Rumah Inap Pekerja | F8: 1100000 | G8: =G7-F8 -> 49900000 | I8: Upah Tukang | J8: =F23+F25+F28+SUM(F31:F33)+F37+F39+F42+SUM(F46:F48)+SUM(F52:F53) -> 13833000
B9: 3 | C9: 46160 | D9: Beli Lampu Kosan Tukang | F9: 100000 | G9: =G8-F9 -> 49800000 | I9: Sewa Alat Proyek
B10: 4 | C10: 46161 | D10: Uang Satpam | F10: 100000 | G10: =G9-F10 -> 49700000 | I10: Transportasi Lapangan | J10: =F20+F41+F44+F49 -> 567000
B11: 5 | C11: 46161 | D11: DP Gorden | F11: 925000 | G11: =G10-F11 -> 48775000 | J11: =SUM(J7:J10) -> 31853043
B12: 6 | C12: 46161 | D12: Print Kontrak dan Materai | F12: 13000 | G12: =G11-F12 -> 48762000
B13: 7 | C13: 46162 | D13: Tips Tukang AC Bobok | F13: 150000 | G13: =G12-F13 -> 48612000 | I13: Kasbon Mas Imam | J13: =F23+F32+F46+F47 -> 6000000
B14: 8 | C14: 46162 | D14: Lalamove Barang Lama | F14: 100000 | G14: =G13-F14 -> 48512000 | I14: Sisa Kasbon Mas Imam | J14: =7500000-J13 -> 1500000
B15: 9 | C15: 46163 | D15: Belanja Bahan Bobokan AC | F15: 323000 | G15: =G14-F15 -> 48189000
B16: 10 | C16: 46163 | D16: Belanja Bahan Interior | F16: 2031000 | G16: =G15-F16 -> 46158000
B17: 11 | C17: 46163 | D17: Belanja Plafon | F17: 989000 | G17: =G16-F17 -> 45169000
B18: 12 | C18: 46163 | D18: Belanja Perintilan Cat | F18: 38000 | G18: =G17-F18 -> 45131000
B19: 13 | C19: 46163 | D19: Belanja LED Strip | F19: 1976600 | G19: =G18-F19 -> 43154400
B20: 14 | C20: 46164 | D20: Lalamove Mesin Gerinda | F20: 65000 | G20: =G19-F20 -> 43089400
B21: 15 | C21: 46164 | D21: Belanja Cat Oplos | F21: 511000 | G21: =G20-F21 -> 42578400
B22: 16 | C22: 46165 | D22: Beli Cat Plafon | F22: 190000 | G22: =G21-F22 -> 42388400
B23: 17 | C23: 46165 | D23: Kasbon Mas Imam | F23: 2000000 | G23: =G22-F23 -> 40388400
B24: 18 | C24: 46165 | D24: Pelunasan Tukang AC | F24: 2265000 | G24: =G23-F24 -> 38123400
B25: 19 | C25: 46165 | D25: Gajian Mang Edi | F25: 700000 | G25: =G24-F25 -> 37423400
B26: 20 | C26: 46167 | D26: Belanja Perintilan | F26: 48000 | G26: =G25-F26 -> 37375400
... B53: 47 | C53: 46187 | D53: Gajian Mang Edi | F53: 200000 | G53: =G52-F53 -> 19146957
B54: Jumlah | E54: =SUM(E7:E53) -> 51000000 | F54: =SUM(F7:F53) -> 31853043 | G54: =E54-F54 -> 19146957
G55: =G54/E54 -> 0.37543053

Sheet CR House - Erick
B2: Time Travel Design
B3: CR House - Erick
B4: Laporan Keuangan
B5: 2026
B6: No | C6: Tanggal | D6: Keterangan | E6: Debit | F6: Kredit | G6: Saldo Akhir | I6: Pengelompokan | J6: Total
B7: 1 | C7: 46160 | D7: Pembayaran Termin I | E7: 8000000 | G7: =E7 -> 8000000 | I7: Bahan Baku Utama / Material | J7: =SUM(F8:F10)+F12+SUM(F15:F16) -> 3937635
B8: 2 | C8: 46163 | D8: Belanja Bahan | F8: 2330000 | G8: =G7-F8 -> 5670000 | I8: Upah Tukang | J8: =F11+F13+F17+F18 -> 4000000
B9: 3 | C9: 46163 | D9: Belanja Perintilan | F9: 85000 | G9: =G8-F9 -> 5585000 | I9: Sewa Alat Proyek
B10: 4 | C10: 46164 | D10: Belanja Cat Oplos | F10: 500000 | G10: =G9-F10 -> 5085000 | I10: Transportasi Lapangan | J10: =F14+SUM(F19:F20) -> 474000
B11: 5 | C11: 46165 | D11: Kasbon Mas Imam | F11: 1500000 | G11: =G10-F11 -> 3585000 | J11: =SUM(J7:J10) -> 8411635
B12: 6 | C12: 46169 | D12: Beli Alat Kompressor | F12: 256770 | G12: =G11-F12 -> 3328230
B13: 7 | C13: 46172 | D13: Kasbon Mas Imam | F13: 1000000 | G13: =G12-F13 -> 2328230 | I13: Kasbon Mas Imam | J13: =F11+F13+F17+F18 -> 4000000
B14: 8 | C14: 46174 | D14: Grab Mas Imam | F14: 105000 | G14: =G13-F14 -> 2223230 | I14: Sisa Kasbon Mas Imam | J14: =4000000-J13 -> 0
B15: 9 | C15: 46175 | D15: Talangin Grease Trap | F15: 478865 | G15: =G14-F15 -> 1744365
B16: 10 | C16: 46177 | D16: Belanja Perintilan | F16: 287000 | G16: =G15-F16 -> 1457365
B17: 11 | C17: 46177 | D17: Kasbon Mas Imam | F17: 1000000 | G17: =G16-F17 -> 457365
B18: 12 | C18: 46180 | D18: Kasbon Mas Imam | F18: 500000 | G18: =G17-F18 -> -42635
B19: 13 | C19: 46180 | D19: Lalamove Interior | F19: 175000 | G19: =G18-F19 -> -217635
B20: 14 | C20: 46180 | D20: Buang Sampah + Tukang Ngikut | F20: 194000 | G20: =G19-F20 -> -411635
B21: 14 | C21: 46181 | D21: Pembayaran Pelunasan | E21: 7000000 | G21: =G20+E21 -> 6588365
B22: Jumlah | E22: =SUM(E7:E21) -> 15000000 | F22: =SUM(F7:F20) -> 8411635 | G22: =E22-F22 -> 6588365
G23: =G22/E22 -> 0.43922433

Sheet TJ House - Tommy Saputra (LT2)
B2: Time Travel Design
B3: TJ House - Pak Tommy
B4: Laporan Keuangan
B5: 2026
B6: No | C6: Tanggal | D6: Keterangan | E6: Debit | F6: Kredit | G6: Saldo Akhir | I6: Pengelompokan | J6: Total
B7: 1 | C7: 46141 | D7: Print Kontrak dan Materai | F7: 31000 | G7: =-F7 -> -31000 | I7: Bahan Baku Utama / Material | J7: =F7+SUM(F9:F11)+SUM(F13:F14)+F16+SUM(F18:F23)+SUM(F25:F26)+SUM(F29:F30)+SUM(F32:F34)+SUM(F36:F39)+SUM(F41:F43)+SUM(F49:F51) -> 25117904
B8: 2 | C8: 46141 | D8: Pembayaran Termin I | E8: 33000000 | G8: =G7+E8 -> 32969000 | I8: Upah Tukang | J8: =F12+F15+F17+F24+F27+F31+F35+F40+SUM(F44:F46)+F48 -> 17800000
B9: 3 | C9: 46144 | D9: Belanja Kebutuhan Multipleks | F9: 8546000 | G9: =G8-F9 -> 24423000 | I9: Sewa Alat Proyek
B10: 4 | C10: 46147 | D10: Belanja Kebutuhan HPL | F10: 3085000 | G10: =G9-F10 -> 21338000 | I10: Transportasi Lapangan | J10: =F28 -> 325000
B11: 5 | C11: 46147 | D11: Belanja Kebutuhan HPL | F11: 2214000 | G11: =G10-F11 -> 19124000 | J11: =SUM(J7:J10) -> 43242904
B12: 6 | C12: 46149 | D12: Kasbon Mas Imam | F12: 1500000 | G12: =G11-F12 -> 17624000
B13: 7 | C13: 46149 | D13: Belanja Edging | F13: 168000 | G13: =G12-F13 -> 17456000 | I13: Kasbon Mas Imam | J13: =F12+F15+F17+F24+F27+F35+F44+F46 -> 14000000
B14: 8 | C14: 46151 | D14: Belanja Perintilan | F14: 645000 | G14: =G13-F14 -> 16811000 | I14: Sisa Kasbon Mas Imam | J14: =14000000-J13 -> 0
B15: 9 | C15: 46151 | D15: Kasbon Mas Imam | F15: 2000000 | G15: =G14-F15 -> 14811000
B16: 10 | C16: 46151 | D16: Token Listrik Bayem | F16: 100000 | G16: =G15-F16 -> 14711000 | I16: Gajian Mang Edi
B17: 11 | C17: 46153 | D17: Kasbon Mas Imam | F17: 1500000 | G17: =G16-F17 -> 13211000
B18: 12 | C18: 46154 | D18: Belanja Perintilan | F18: 436000 | G18: =G17-F18 -> 12775000
B19: 13 | C19: 46154 | D19: Belanja Cat Oplos | F19: 327000 | G19: =G18-F19 -> 12448000
B20: 14 | C20: 46155 | D20: Belanja Rel Slide | F20: 240000 | G20: =G19-F20 -> 12208000
B21: 15 | C21: 46155 | D21: Belanja Pilok | F21: 94000 | G21: =G20-F21 -> 12114000
B22: 16 | C22: 46155 | D22: DP Cermin | F22: 1120000 | G22: =G21-F22 -> 10994000
B23: 17 | C23: 46156 | D23: Beli Lem Kuning | F23: 165000 | G23: =G22-F23 -> 10829000
B24: 18 | C24: 46156 | D24: Kasbon Mas Imam | F24: 1500000 | G24: =G23-F24 -> 9329000
B25: 19 | C25: 46157 | D25: Belanja Perintilan | F25: 104000 | G25: =G24-F25 -> 9225000
B26: 20 | C26: 46158 | D26: Belanja Edging | F26: 95000 | G26: =G25-F26 -> 9130000
B27: 21 | C27: 46158 | D27: Kasbon Mas Imam | F27: 3500000 | G27: =G26-F27 -> 5630000
B28: 22 | C28: 46160 | D28: Lalamove Pengiriman Interior | F28: 325000 | G28: =G27-F28 -> 5305000
... B46: 40 | C46: 46165 | D46: Kasbon Mas Imam | F46: 2000000 | G46: =G45-F46 -> -8091904
B47: 41 | C47: 46165 | D47: Pembayaran Termin II | E47: 16500000 | G47: =G46+E47 -> 8408096
B48: 42 | C48: 46168 | D48: Upah Mas Eko | F48: 1300000 | G48: =G47-F48 -> 7108096
B49: 43 | C49: 46169 | D49: Wall Mounted Lamp | F49: 565000 | G49: =G48-F49 -> 6543096
B50: 44 | C50: 46177 | D50: Belanja Perintilan | F50: 206000 | G50: =G49-F50 -> 6337096
B51: 45 | C51: 46178 | D51: Beli Taco Sheet | F51: 80000 | G51: =G50-F51 -> 6257096
B52: 46 | C52: 46182 | D52: Pembayaran Tahap Pelunasan | E52: 16500000 | G52: =G51+E52 -> 22757096
B53: Jumlah | E53: =SUM(E7:E52) -> 66000000 | F53: =SUM(F7:F52) -> 43242904 | G53: =E53-F53 -> 22757096
G54: =G53/E53 -> 0.34480448

Sheet TJ House - Tommy Saputra (LT1)
B2: Time Travel Design
B3: TJ House - Pak Tommy
B4: Laporan Keuangan
B5: 2026
B6: No | C6: Tanggal | D6: Keterangan | E6: Debit | F6: Kredit | G6: Saldo Akhir | I6: Pengelompokan | J6: Total
B7: 1 | C7: 46098 | D7: Print Kontrak dan Materai | F7: 29000 | G7: =F7 -> 29000 | I7: Bahan Baku Utama / Material | J7: =F7+SUM(F9:F11)+SUM(F13:F15)+SUM(F18:F20)+F22+SUM(F24:F29)+SUM(F32:F33)+F35+SUM(F37:F41)+F43+SUM(F45:F48)+F50+SUM(F52:F56)+F59 -> 38502983
B8: 2 | C8: 46106 | D8: Pembayaran Tahap I | E8: 35000000 | G8: =E8-G7 -> 34971000 | I8: Upah Tukang | J8: =F12+F16+F23+F31+F34+F42+F51+F58 -> 18200000
B9: 3 | C9: 46108 | D9: Print Gambar | F9: 10000 | G9: =G8-F9 -> 34961000 | I9: Sewa Alat Proyek
B10: 4 | C10: 46108 | D10: Belanja Bahan Awal | F10: 7055000 | G10: =G9-F10 -> 27906000 | I10: Transportasi Lapangan | J10: =F17+F21+F30+F36+F44 -> 1937500
B11: 5 | C11: 46111 | D11: Print Gambar | F11: 60000 | G11: =G10-F11 -> 27846000 | J11: =SUM(J7:J10) -> 58640483
B12: 6 | C12: 46111 | D12: Kasbon Mas Imam | F12: 1000000 | G12: =G11-F12 -> 26846000
B13: 7 | C13: 46112 | D13: Belanja Kabel | F13: 56500 | G13: =G12-F13 -> 26789500 | I13: Kasbon Mas Imam | J13: =F12+F16+F23+F31+F34+F51+F58 -> 17200000
B14: 8 | C14: 46113 | D14: Belanja HPL dan Perintilan | F14: 7914000 | G14: =G13-F14 -> 18875500 | I14: Sisa Kasbon Mas Imam | J14: =17200000-J13 -> 0
B15: 9 | C15: 46114 | D15: Belanja Bahan Tambah | F15: 1104000 | G15: =G14-F15 -> 17771500
B16: 10 | C16: 46114 | D16: Kasbon Mas Imam | F16: 2000000 | G16: =G15-F16 -> 15771500
B17: 11 | C17: 46115 | D17: Bensin dan Token Listrik | F17: 100000 | G17: =G16-F17 -> 15671500
B18: 12 | C18: 46115 | D18: Edging HPL | F18: 285000 | G18: =G17-F18 -> 15386500
B19: 13 | C19: 46115 | D19: Taco Sheet | F19: 120000 | G19: =G18-F19 -> 15266500
B20: 14 | C20: 46115 | D20: Belanja Kabel | F20: 143500 | G20: =G19-F20 -> 15123000
B21: 15 | C21: 46116 | D21: Pengiriman Interior Lalamove | F21: 300000 | G21: =G20-F21 -> 14823000
B22: 16 | C22: 46116 | D22: Belanja Kabel | F22: 700000 | G22: =G21-F22 -> 14123000
B23: 17 | C23: 46116 | D23: Kasbon Mas Imam | F23: 2000000 | G23: =G22-F23 -> 12123000
B24: 18 | C24: 46117 | D24: Saklar Lampu | F24: 445000 | G24: =G23-F24 -> 11678000
B25: 19 | C25: 46118 | D25: Granite Tile 3 Lembar | F25: 7213760 | G25: =G24-F25 -> 4464240
B26: 20 | C26: 46118 | D26: Bahan Tambahan | F26: 735000 | G26: =G25-F26 -> 3729240
... B48: 42 | C48: 46129 | D48: Rak Susun Piring | F48: 108799 | G48: =G47-F48 -> -16622483
B49: 43 | C49: 46130 | D49: Pembayaran Tahap II + Pekerjaan Tambah | E49: 21300000 | G49: =G48+E49 -> 4677517
B50: 44 | C50: 46130 | D50: Lemari Tangga TJ House | F50: 710000 | G50: =G49-F50 -> 3967517
B51: 45 | C51: 46130 | D51: Kasbon Mas Imam | F51: 3000000 | G51: =G50-F51 -> 967517
B52: 46 | C52: 46131 | D52: Bahan Tambahan | F52: 631000 | G52: =G51-F52 -> 336517
B53: 47 | C53: 46134 | D53: Rak Sendok dan Garpu | F53: 136400 | G53: =G52-F53 -> 200117
B54: 48 | C54: 46135 | D54: Makan dan Beli Handle | F54: 123600 | G54: =G53-F54 -> 76517
B55: 49 | C55: 46139 | D55: Belanja Gantungan Baju | F55: 100000 | G55: =G54-F55 -> -23483
B56: 50 | C56: 46140 | D56: Sealant Odol | F56: 20000 | G56: =G55-F56 -> -43483
B57: 51 | C57: 46140 | D57: Pelunasan Interior Tahap I | E57: 19300000 | G57: =G56+E57 -> 19256517
B58: 52 | C58: 46144 | D58: Pelunasan Borongan Mas Imam | F58: 2200000 | G58: =G57-F58 -> 17056517
B59: 53 | C59: 46144 | D59: Belanja Perintilan Retensi | F59: 97000 | G59: =G58-F59 -> 16959517
B60: Jumlah | E60: =SUM(E7:E59) -> 75600000 | F60: =SUM(F7:F59) -> 58640483 | G60: =E60-F60 -> 16959517
G61: =G60/E60 -> 0.22433224

Sheet SJ House - Tria Andika (LT1)
B2: Time Travel Design
B3: SJ House - Mas Arya
B4: Laporan Keuangan
B5: 2026
B6: No | C6: Tanggal | D6: Keterangan | E6: Debit | F6: Kredit | G6: Saldo Akhir | I6: Pengelompokan | J6: Total
B7: 1 | C7: 46039 | D7: Pembayaran Tahap Deposit | E7: 1500000 | G7: =E7 -> 1500000 | I7: Bahan Baku Utama / Material | J7: =SUM(F8:F9)+SUM(F12:F14)+F16+SUM(F18:F21)+SUM(F23:F24)+SUM(F30:F35)+SUM(F37:F41)+SUM(F46:F47)+F52+SUM(F56:F58)+F60+F64+SUM(F70:F72)+F74+F79+SUM(F81:F83)+SUM(F85:F89)+SUM(F94:F95)+SUM(F98:F100)+SUM(F103:F105)+SUM(F109:F112)+F114+F116+F118+SUM(F121:F122)+SUM(F125:F136)+SUM(F141:F143)+F146+SUM(F148:F152)+F154+SUM(F156:F159)+SUM(F161:F164)+F166+SUM(F168:F173)+SUM(F176:F177)+F181 -> 104219718
B8: 2 | C8: 46079 | D8: Print Gambar dan RAB | F8: 53000 | G8: =G7-F8 -> 1447000 | I8: Upah Tukang | J8: =F11+F15+F17+F22+F29+F36+F42+F51++F53+F55+SUM(F65:F68)+F73+SUM(F75:F76)+F78+SUM(F91:F92)+F101+F106+F113+F117+F123+SUM(F139:F140)+SUM(F144:F145)+F153+F155+F167+SUM(F178:F180)+F183+F184 -> 78367000
B9: 3 | C9: 46083 | D9: Print RAB dan Kontrak | F9: 30000 | G9: =G8-F9 -> 1417000 | I9: Sewa Alat Proyek
B10: 4 | C10: 46083 | D10: DP Termin 1 | E10: 90000000 | G10: =G9+E10 -> 91417000 | I10: Transportasi Lapangan | J10: =SUM(F25:F28)+F45+SUM(F48:F50)+F54+F59+SUM(F61:F63)+F69+F77+F80+F90+F93+SUM(F96:F97)+F102+F107+F115+F120+F124+SUM(F137:F138)+F147+F160+SUM(F174:F175)+F182 -> 6790800
B11: 5 | C11: 46083 | D11: Kasbon Mas Imam | F11: 1000000 | G11: =G10-F11 -> 90417000 | J11: =SUM(J7:J10) -> 189377518
B12: 6 | C12: 46084 | D12: Print Gambar Mas Imam | F12: 44000 | G12: =G11-F12 -> 90373000
B13: 7 | C13: 46085 | D13: Belanja Bahan | F13: 10350000 | G13: =G12-F13 -> 80023000
B14: 8 | C14: 46085 | D14: Beli Gembok | F14: 42500 | G14: =G13-F14 -> 79980500
B15: 9 | C15: 46085 | D15: Kasbon Mas Imam | F15: 1000000 | G15: =G14-F15 -> 78980500
B16: 10 | C16: 46085 | D16: Beli Terpal, dll | F16: 200000 | G16: =G15-F16 -> 78780500
B17: 11 | C17: 46087 | D17: Kasbon Mang Edi | F17: 200000 | G17: =G16-F17 -> 78580500
B18: 12 | C18: 46088 | D18: Print dan Materai | F18: 18000 | G18: =G17-F18 -> 78562500
B19: 13 | C19: 46088 | D19: Belanja Bahan Plafon | F19: 2570000 | G19: =G18-F19 -> 75992500
B20: 14 | C20: 46088 | D20: Belanja HPL | F20: 3861000 | G20: =G19-F20 -> 72131500
B21: 15 | C21: 46088 | D21: DP Gorden | F21: 1375000 | G21: =G20-F21 -> 70756500
B22: 16 | C22: 46088 | D22: Kasbon Mas Imam | F22: 3000000 | G22: =G21-F22 -> 67756500
B23: 17 | C23: 46088 | D23: Belanja Bahan Meja Kerja Mas Imam | F23: 360000 | G23: =G22-F23 -> 67396500
... B42: 36 | C42: 46092 | D42: Kasbon Mas Imam | F42: 1000000 | G42: =G41-F42 -> 48659100
B43: 37 | C43: 46092 | D43: Pembayaran Tahap II | E43: 45000000 | G43: =G42+E43 -> 93659100
B44: 38 | C44: 46092 | D44: Transportasi Barang Mitra 10 | E44: 400000 | G44: =G43+E44 -> 94059100
B45: 39 | C45: 46092 | D45: Reimburse Transport Dustin | F45: 227500 | G45: =G44-F45 -> 93831600
B46: 40 | C46: 46092 | D46: Cat Oplos | F46: 160000 | G46: =G45-F46 -> 93671600
B47: 41 | C47: 46093 | D47: LED Strip Inlite | F47: 1657275 | G47: =G46-F47 -> 92014325
B48: 42 | C48: 46093 | D48: Uang Kopi Satpam Jasmia | F48: 100000 | G48: =G47-F48 -> 91914325
B49: 43 | C49: 46093 | D49: Lalamove Barang | F49: 400000 | G49: =G48-F49 -> 91514325
B50: 44 | C50: 46094 | D50: Uang Kopi Satpam Jasmia | F50: 50000 | G50: =G49-F50 -> 91464325
B51: 45 | C51: 46094 | D51: Kasbon Mas Imam | F51: 2000000 | G51: =G50-F51 -> 89464325
B52: 46 | C52: 46094 | D52: Beli Perintilan Barang | F52: 203000 | G52: =G51-F52 -> 89261325
B53: 47 | C53: 46094 | D53: Kasbon Mang Edi | F53: 500000 | G53: =G52-F53 -> 88761325
B54: 48 | C54: 46094 | D54: Lalamove Barang | F54: 412500 | G54: =G53-F54 -> 88348825
B55: 49 | C55: 46095 | D55: Kasbon Mas Imam | F55: 6500000 | G55: =G54-F55 -> 81848825
B56: 50 | C56: 46095 | D56: Belanja Tambahan | F56: 611000 | G56: =G55-F56 -> 81237825
... B83: 77 | C83: 46113 | D83: List Gypsum Plafon | F83: 223500 | G83: =G82-F83 -> 62644881
B84: 78 | C84: 46113 | D84: Pembayaran Pekerjaan Tambah | E84: 10000000 | G84: =G83+E84 -> 72644881
B85: 79 | C85: 46114 | D85: Belanja Pipa Listrik dan Perintilan | F85: 140000 | G85: =G84-F85 -> 72504881
B86: 80 | C86: 46114 | D86: DP Pintu Kaca dan Cermin | F86: 1055000 | G86: =G85-F86 -> 71449881
B87: 81 | C87: 46114 | D87: Belanja Tambahan Lampu | F87: 416660 | G87: =G86-F87 -> 71033221
B88: 82 | C88: 46114 | D88: Belanja Granite Tile Kitchen | F88: 4348000 | G88: =G87-F88 -> 66685221
B89: 83 | C89: 46115 | D89: Embow Dus dan Kabel | F89: 186000 | G89: =G88-F89 -> 66499221
B90: 84 | C90: 46116 | D90: Pengiriman Interior Lalamove | F90: 300000 | G90: =G89-F90 -> 66199221
B91: 85 | C91: 46116 | D91: Gajian Mang Edi | F91: 1450000 | G91: =G90-F91 -> 64749221
B92: 86 | C92: 46116 | D92: Kasbon Mas Imam | F92: 4000000 | G92: =G91-F92 -> 60749221
B93: 87 | C93: 46117 | D93: Reimburse Transport Emir (Anter dan Cari Bahan) | F93: 407000 | G93: =G92-F93 -> 60342221
B94: 88 | C94: 46118 | D94: Belanja Kabel Lan dan Kabel Antena | F94: 87000 | G94: =G93-F94 -> 60255221
B95: 89 | C95: 46118 | D95: Pelunasan Pintu Kaca Alumunium | F95: 1055000 | G95: =G94-F95 -> 59200221
B96: 90 | C96: 46118 | D96: Reimburse Transport Dustin (Ops dan Sofa) | F96: 150000 | G96: =G95-F96 -> 59050221
... B107: 101 | C107: 46120 | D107: Angkut Sampah | F107: 250000 | G107: =G106-F107 -> 32584721
B108: 102 | C108: 46122 | D108: Pelunasan Custom Sofa | E108: 38000000 | G108: =G107+E108 -> 70584721
B109: 103 | C109: 46122 | D109: Belanja Bahan Musholla | F109: 859000 | G109: =G108-F109 -> 69725721
B110: 104 | C110: 46122 | D110: Kebutuhan Tambahan Dapur | F110: 60000 | G110: =G109-F110 -> 69665721
B111: 105 | C111: 46122 | D111: Pelunasan Kaca Film dan Pintu Kaca Kitchen | F111: 5800000 | G111: =G110-F111 -> 63865721
B112: 106 | C112: 46123 | D112: Belanja Tambahan Rak Musholla | F112: 1171000 | G112: =G111-F112 -> 62694721
B113: 107 | C113: 46123 | D113: Gajian Mang Edi | F113: =1900000+540000 -> 2440000 | G113: =G112-F113 -> 60254721
B114: 108 | C114: 46123 | D114: Belanja Bahan Perintilan | F114: 286000 | G114: =G113-F114 -> 59968721
B115: 109 | C115: 46123 | D115: Reimburse Bensin Dustin | F115: 100000 | G115: =G114-F115 -> 59868721
B116: 110 | C116: 46125 | D116: Belanja Bahan Musholla | F116: 1850000 | G116: =G115-F116 -> 58018721
B117: 111 | C117: 46126 | D117: Kasbon Mang Edi | F117: 1000000 | G117: =G116-F117 -> 57018721
B118: 112 | C118: 46127 | D118: Print Gambar Lantai 2 | F118: 37500 | G118: =G117-F118 -> 56981221
B119: 113 | C119: 46127 | D119: DP Tahap 2 Lantai 1 | E119: 18000000 | G119: =G118+E119 -> 74981221
B120: 114 | C120: 46127 | D120: Pengiriman Interior Lalamove | F120: 165000 | G120: =G119-F120 -> 74816221
B121: 115 | C121: 46127 | D121: WPC Tambahan | F121: 700000 | G121: =G120-F121 -> 74116221
B122: 116 | C122: 46127 | D122: Mohair Pintu | F122: 105500 | G122: =G121-F122 -> 74010721
B123: 117 | C123: 46127 | D123: Kasbon Mas Imam | F123: 1500000 | G123: =G122-F123 -> 72510721
B124: 118 | C124: 46127 | D124: Gojek Dustin | F124: 40000 | G124: =G123-F124 -> 72470721
B125: 119 | C125: 46128 | D125: Stop Kontak dan Kabel | F125: 290000 | G125: =G124-F125 -> 72180721
B126: 120 | C126: 46128 | D126: Push On | F126: 185000 | G126: =G125-F126 -> 71995721
B127: 121 | C127: 46128 | D127: Mata Bor | F127: 80000 | G127: =G126-F127 -> 71915721
B128: 122 | C128: 46128 | D128: Lem Tetes dan Lakban | F128: 121000 | G128: =G127-F128 -> 71794721
B129: 123 | C129: 46128 | D129: Wall Moulding PVC | F129: 393100 | G129: =G128-F129 -> 71401621
B130: 124 | C130: 46128 | D130: DP Mihrab | F130: 762500 | G130: =G129-F130 -> 70639121
B131: 125 | C131: 46128 | D131: Tulisan Allah Musholla | F131: 276608 | G131: =G130-F131 -> 70362513
... B164: 158 | C164: 46134 | D164: Belanja Perintilan | F164: 290000 | G164: =G163-F164 -> 34179774
B165: 159 | C165: 46134 | D165: Pembayaran Termin III | E165: 50000000 | G165: =G164+E165 -> 84179774
B166: 160 | C166: 46135 | D166: Pelunasan Sofa | F166: 2250000 | G166: =G165-F166 -> 81929774
B167: 161 | C167: 46135 | D167: Kasbon Mas Imam | F167: 1000000 | G167: =G166-F167 -> 80929774
B168: 162 | C168: 46135 | D168: Oplos Cat Duco | F168: 298000 | G168: =G167-F168 -> 80631774
B169: 163 | C169: 46135 | D169: Pelunasan WPC | F169: 600000 | G169: =G168-F169 -> 80031774
B170: 164 | C170: 46135 | D170: Cat dan Lampu Musholla | F170: 192292 | G170: =G169-F170 -> 79839482
B171: 165 | C171: 46136 | D171: Belanja Perintilan Cat | F171: 107000 | G171: =G170-F171 -> 79732482
B172: 166 | C172: 46136 | D172: Belanja List Gypsum Musholla | F172: 45000 | G172: =G171-F172 -> 79687482
B173: 167 | C173: 46136 | D173: Pelunasan Gorden | F173: 480000 | G173: =G172-F173 -> 79207482
B174: 168 | C174: 46136 | D174: Angkut Sampah | F174: 250000 | G174: =G173-F174 -> 78957482
B175: 169 | C175: 46137 | D175: Lalamove | F175: 375000 | G175: =G174-F175 -> 78582482
B176: 170 | C176: 46137 | D176: Beli Bahan Bersih Bersih | F176: 50000 | G176: =G175-F176 -> 78532482
B177: 171 | C177: 46137 | D177: Sewa Alat Duco | F177: 400000 | G177: =G176-F177 -> 78132482
... B184: 178 | C184: 46144 | D184: Pelunasan Borongan Mas Imam | F184: 1100000 | G184: =G183-F184 -> 63522482
B185: 179 | C185: 46150 | D185: Pelunasan Tahap Serah Terima | E185: 20500000 | G185: =G184+E185 -> 84022482
B186: Jumlah | E186: =SUM(E7:E185) -> 273400000 | F186: =SUM(F7:F185) -> 189377518 | G186: =E186-F186 -> 84022482
G187: =G186/E186 -> 0.30732437

Sheet YP House - Yerry Primadi
B2: Time Travel Design
B3: YP House (Design) - Mas Yerry
B4: Laporan Keuangan
B5: 2026
B6: No | C6: Tanggal | D6: Keterangan | E6: Debit | F6: Kredit | G6: Saldo Akhir | I6: Pengelompokan | J6: Total
B7: 1 | C7: 46039 | D7: Pembayaran Tahap Pelunasan | E7: 1800000 | G7: =E7 -> 1800000 | I7: Bahan Baku Utama / Material | J7: =F9 -> 163000
B8: 2 | C8: 46061 | D8: Pembayaran Tahap I Revisi | E8: 3000000 | G8: =G7+E8 -> 4800000 | I8: Upah Tukang
B9: 3 | C9: 46069 | D9: Print Gambar Warisman | F9: 163000 | G9: =G8-F9 -> 4637000 | I9: Sewa Alat Proyek
B10: 4 | C10: 46069 | D10: Pembayaran Tahap Pelunasan | E10: 1000000 | G10: =G9+E10 -> 5637000 | I10: Transportasi Lapangan
B11: Jumlah | E11: =SUM(E7:E10) -> 5800000 | F11: =SUM(F7:F10) -> 163000 | G11: =E11-F11 -> 5637000
